<HBProfile creator="Cava">
<Name>[H-Quest] (5-11) Tirisfal Glades [Cava] $Rev$</Name>
<MinLevel>1</MinLevel><MaxLevel>91</MaxLevel><MinDurability>0.2</MinDurability><MinFreeBagSlots>2</MinFreeBagSlots><TargetElites>False</TargetElites>
<MailGrey>False</MailGrey><MailWhite>False</MailWhite><MailGreen>True</MailGreen><MailBlue>True</MailBlue><MailPurple>True</MailPurple>
<SellGrey>True</SellGrey><SellWhite>True</SellWhite><SellGreen>False</SellGreen><SellBlue>False</SellBlue><SellPurple>False</SellPurple>

<AvoidMobs>
  <Mob Name="Farmer Solliden" Entry="1936"/>
  <Mob Name="Muad" Entry="1910"/>
</AvoidMobs>
<Blackspots>
  <Blackspot X="2595.883" Y="1462.359" Z="-8.474638" Radius="5" />
</Blackspots>

<Mailboxes>
  <Mailbox X="2266.247" Y="290.7186" Z="33.69072" />
</Mailboxes>

<Vendors>
  <Vendor Name="Franklin Brinklestein" Entry="44034" Type="Food" X="2234.77" Y="1021.9" Z="36.44947" />
  <Vendor Name="Innkeeper Renee" Entry="5688" Type="Food" X="2285.95" Y="282.613" Z="33.24683" />
  <Vendor Name="Provisioner Elda" Entry="46271" Type="Food" X="1668.34" Y="-720.995" Z="58.91577" />
  <Vendor Name="Gordo" Entry="10666" Type="Repair" X="2240.053" Y="1024.575" Z="36.45156" />
  <Vendor Name="Eliza Callen" Entry="2137" Type="Repair" X="2302.86" Y="288.523" Z="33.3571" />
  <Vendor Name="Argent Quartermaster Hasana" Entry="10856" Type="Repair" X="1784.72" Y="-729.1077" Z="59.82564" />
  <Vendor Name="Kramlod Farsight" Entry="44040" Type="Repair" X="1740.21" Y="-731.88" Z="60.06553" />
</Vendors>
<!-- ####################################### Quest Overrides ####################################################################### -->
<Quest Id="24975" Name="Fields of Grief">
  <Objective Type="CollectItem" ItemId="2846" CollectCount="10">
    <CollectFrom>
	<GameObject Name="Tirisfal Pumpkin" Id="375" />
    </CollectFrom>
    <Hotspots>
      <Hotspot X="2277.678" Y="1186.542" Z="31.59063" />
      <Hotspot X="2270.899" Y="1226.348" Z="31.44313" />
      <Hotspot X="2269.781" Y="1267.365" Z="31.44313" />
      <Hotspot X="2275.834" Y="1307.699" Z="33.17928" />
      <Hotspot X="2281.219" Y="1348.388" Z="33.33342" />
      <Hotspot X="2282.375" Y="1388.866" Z="33.33342" />
      <Hotspot X="2300.637" Y="1425.882" Z="33.33342" />
      <Hotspot X="2336.227" Y="1404.378" Z="33.32778" />
      <Hotspot X="2329.941" Y="1364.516" Z="33.33197" />
    </Hotspots>
  </Objective>
</Quest>
<Quest Id="24978" Name="Reaping the Reapers">
  <Objective Type="KillMob" MobId="1934" KillCount="10">
    <Hotspots>
      <Hotspot X="2277.678" Y="1186.542" Z="31.59063" />
      <Hotspot X="2270.899" Y="1226.348" Z="31.44313" />
      <Hotspot X="2269.781" Y="1267.365" Z="31.44313" />
      <Hotspot X="2275.834" Y="1307.699" Z="33.17928" />
      <Hotspot X="2281.219" Y="1348.388" Z="33.33342" />
      <Hotspot X="2282.375" Y="1388.866" Z="33.33342" />
      <Hotspot X="2300.637" Y="1425.882" Z="33.33342" />
      <Hotspot X="2336.227" Y="1404.378" Z="33.32778" />
      <Hotspot X="2329.941" Y="1364.516" Z="33.33197" />
    </Hotspots>
  </Objective>
</Quest>
<Quest Id="24976" Name="Variety is the Spice of Death">
  <Objective Type="CollectItem" ItemId="52067" CollectCount="4">
    <CollectFrom>
	<GameObject Name="Marrowpetal Stalk" Id="202422" />
    </CollectFrom>
    <Hotspots>
      <Hotspot X="2158.006" Y="831.394" Z="30.59422" />
      <Hotspot X="2144.956" Y="792.9863" Z="30.37889" />
      <Hotspot X="2181.522" Y="776.7186" Z="30.69724" />
      <Hotspot X="2221.188" Y="784.9879" Z="30.69728" />
      <Hotspot X="2243.342" Y="818.3333" Z="30.69731" />
      <Hotspot X="2205.054" Y="831.7079" Z="30.69724" />
    </Hotspots>
  </Objective>
  <Objective Type="CollectItem" ItemId="52066" CollectCount="4">
    <CollectFrom>
	<GameObject Name="Xavren's Thorn" Id="202421" />
    </CollectFrom>
    <Hotspots>
      <Hotspot X="2658.471" Y="1211.17" Z="68.27221" />
      <Hotspot X="2667.848" Y="1250.542" Z="59.13974" />
      <Hotspot X="2678.117" Y="1288.851" Z="50.05188" />
      <Hotspot X="2697.031" Y="1324.094" Z="40.73071" />
      <Hotspot X="2660.194" Y="1339.117" Z="32.64879" />
      <Hotspot X="2620.742" Y="1331.085" Z="37.63914" />
      <Hotspot X="2579.615" Y="1329.32" Z="33.82281" />
      <Hotspot X="2541.261" Y="1343.612" Z="25.7986" />
      <Hotspot X="2507.506" Y="1361.455" Z="12.63498" />
      <Hotspot X="2473.954" Y="1383.745" Z="15.37792" />
      <Hotspot X="2454.531" Y="1418.119" Z="24.77365" />
    </Hotspots>
  </Objective>
  <Objective Type="CollectItem" ItemId="52068" CollectCount="8">
    <CollectFrom>
	<Mob Name="Briny Sea Cucumber" Id="38933" />
    </CollectFrom>
    <Hotspots>
      <Hotspot X="2572.227" Y="1464.295" Z="-4.508661" />
      <Hotspot X="2605.931" Y="1442.583" Z="-5.103283" />
      <Hotspot X="2636.316" Y="1469.144" Z="-6.525883" />
      <Hotspot X="2619.359" Y="1505.458" Z="-7.216598" />
      <Hotspot X="2584.579" Y="1525.971" Z="-8.101376" />
      <Hotspot X="2570.129" Y="1488.099" Z="-7.015973" />
    </Hotspots>
  </Objective>
</Quest>
<Quest Id="24980" Name="The Scarlet Palisade">
  <Objective Type="KillMob" MobId="1535" KillCount="10">
    <Hotspots>
      <Hotspot X="2384.22" Y="1409.315" Z="34.44831" />
      <Hotspot X="2387.65" Y="1449.644" Z="34.43085" />
      <Hotspot X="2389.879" Y="1489.681" Z="33.70216" />
      <Hotspot X="2407.781" Y="1527.05" Z="32.55365" />
      <Hotspot X="2416.097" Y="1566.771" Z="32.60154" />
      <Hotspot X="2396.632" Y="1602.792" Z="33.51886" />
      <Hotspot X="2356.469" Y="1600.489" Z="35.57378" />
      <Hotspot X="2350.626" Y="1560.786" Z="34.33483" />
      <Hotspot X="2368.409" Y="1524.57" Z="36.35016" />
    </Hotspots>
  </Objective>
</Quest>
<Quest Id="25038" Name="Gordo's Task">
  <Objective Type="CollectItem" ItemId="12737" CollectCount="3">
    <CollectFrom>
	<GameObject Name="Gloom Weed" Id="175566" />
    </CollectFrom>
    <Hotspots>
      <Hotspot X="2137.913" Y="909.0836" Z="33.33007" />
      <Hotspot X="2160.258" Y="875.9286" Z="36.40561" />
      <Hotspot X="2200.048" Y="879.7657" Z="43.34615" />
      <Hotspot X="2233.549" Y="901.9367" Z="46.20908" />
      <Hotspot X="2253.264" Y="937.1023" Z="42.05201" />
      <Hotspot X="2274.454" Y="972.0472" Z="38.74037" />
      <Hotspot X="2276.379" Y="1012.009" Z="36.52707" />
      <Hotspot X="2275.341" Y="1052.431" Z="32.99792" />
      <Hotspot X="2259.523" Y="1090.485" Z="33.13689" />
      <Hotspot X="2223.548" Y="1109.493" Z="30.42314" />
      <Hotspot X="2182.745" Y="1104.955" Z="32.29249" />
      <Hotspot X="2148.55" Y="1083.384" Z="31.76416" />
      <Hotspot X="2121.306" Y="1054.174" Z="35.30317" />
      <Hotspot X="2094.823" Y="1023.707" Z="33.47231" />
      <Hotspot X="2074.794" Y="989.0338" Z="34.40826" />
      <Hotspot X="2064.397" Y="950.3776" Z="38.40001" />
      <Hotspot X="2052.35" Y="911.7637" Z="33.52496" />
      <Hotspot X="2049.113" Y="870.5968" Z="33.88657" />
      <Hotspot X="2058.331" Y="831.672" Z="37.08166" />
      <Hotspot X="2077.307" Y="796.4481" Z="33.73436" />
    </Hotspots>
  </Objective>
</Quest>
<Quest Id="25090" Name="A Putrid Task">
  <Objective Type="CollectItem" ItemId="2855" CollectCount="7">
    <CollectFrom>
	  <Mob Name="Rotting Dead" Id="1525" />
	  <Mob Name="Ravaged Corpse" Id="1526" />
    </CollectFrom>
    <Hotspots>
      <Hotspot X="2109.312" Y="667.1419" Z="35.40836" />
      <Hotspot X="2086.51" Y="633.6898" Z="34.82196" />
      <Hotspot X="2117.883" Y="606.5928" Z="35.01793" />
      <Hotspot X="2157.699" Y="614.4913" Z="35.42235" />
      <Hotspot X="2196.789" Y="622.3149" Z="25.75469" />
      <Hotspot X="2234.554" Y="636.6392" Z="24.79072" />
      <Hotspot X="2275.896" Y="636.8591" Z="25.41044" />
      <Hotspot X="2314.943" Y="645.9803" Z="30.81608" />
      <Hotspot X="2286.858" Y="674.7232" Z="34.17198" />
      <Hotspot X="2251.92" Y="696.2643" Z="34.88637" />
      <Hotspot X="2223.33" Y="667.4566" Z="35.68647" />
    </Hotspots>
  </Objective>
</Quest>
<Quest Id="24990" Name="Darkhound Pounding">
  <Objective Type="CollectItem" ItemId="2858" CollectCount="5">
    <CollectFrom>
	  <Mob Name="Cursed Darkhound" Id="1548" />
    </CollectFrom>
    <Hotspots>
      <Hotspot X="2187.673" Y="313.7323" Z="35.65869" />
      <Hotspot X="2181.305" Y="353.7985" Z="42.85993" />
      <Hotspot X="2157.185" Y="385.4195" Z="50.10912" />
      <Hotspot X="2119.765" Y="399.8929" Z="53.63862" />
      <Hotspot X="2085.056" Y="420.2378" Z="58.27397" />
      <Hotspot X="2048.016" Y="436.0151" Z="48.04784" />
      <Hotspot X="2018.924" Y="463.3003" Z="40.28649" />
      <Hotspot X="1996.334" Y="496.5455" Z="36.81657" />
      <Hotspot X="1970.679" Y="527.4138" Z="42.07484" />
      <Hotspot X="1941.554" Y="554.2789" Z="50.88175" />
      <Hotspot X="1904.798" Y="569.9554" Z="47.2686" />
      <Hotspot X="1869.753" Y="551.5902" Z="39.22961" />
      <Hotspot X="1882.041" Y="512.4634" Z="37.4883" />
      <Hotspot X="1900.35" Y="476.6878" Z="37.80049" />
      <Hotspot X="1908.381" Y="435.8369" Z="34.61976" />
      <Hotspot X="1935.369" Y="406.5072" Z="39.72733" />
      <Hotspot X="1966.679" Y="381.345" Z="35.24394" />
      <Hotspot X="2000.168" Y="358.24" Z="40.22854" />
      <Hotspot X="2039.151" Y="372.3969" Z="42.05231" />
      <Hotspot X="2079.552" Y="363.7648" Z="43.24469" />
      <Hotspot X="2113.256" Y="343.2099" Z="50.0988" />
    </Hotspots>
  </Objective>
</Quest>
<Quest Id="24981" Name="A Thorn in our Side">
  <Objective Type="KillMob" MobId="1536" KillCount="3">
    <Hotspots>
      <Hotspot X="1847.026" Y="662.832" Z="41.66972" />
      <Hotspot X="1830.107" Y="625.7269" Z="41.80838" />
      <Hotspot X="1793.754" Y="606.4429" Z="39.81754" />
      <Hotspot X="1760.679" Y="629.6718" Z="41.22786" />
      <Hotspot X="1759.873" Y="670.2471" Z="42.45318" />
      <Hotspot X="1757.487" Y="710.5906" Z="45.34721" />
      <Hotspot X="1767.335" Y="749.0916" Z="52.40147" />
      <Hotspot X="1805.433" Y="762.2025" Z="44.13055" />
      <Hotspot X="1835.925" Y="734.0191" Z="42.46064" />
      <Hotspot X="1836.128" Y="693.3918" Z="41.43217" />
      <Hotspot X="1833.924" Y="651.8715" Z="43.1892" />
    </Hotspots>
  </Objective>
  <Objective Type="KillMob" MobId="1537" KillCount="3">
    <Hotspots>
      <Hotspot X="1847.026" Y="662.832" Z="41.66972" />
      <Hotspot X="1830.107" Y="625.7269" Z="41.80838" />
      <Hotspot X="1793.754" Y="606.4429" Z="39.81754" />
      <Hotspot X="1760.679" Y="629.6718" Z="41.22786" />
      <Hotspot X="1759.873" Y="670.2471" Z="42.45318" />
      <Hotspot X="1757.487" Y="710.5906" Z="45.34721" />
      <Hotspot X="1767.335" Y="749.0916" Z="52.40147" />
      <Hotspot X="1805.433" Y="762.2025" Z="44.13055" />
      <Hotspot X="1835.925" Y="734.0191" Z="42.46064" />
      <Hotspot X="1836.128" Y="693.3918" Z="41.43217" />
      <Hotspot X="1833.924" Y="651.8715" Z="43.1892" />
    </Hotspots>
  </Objective>
  <Objective Type="CollectItem" ItemId="52077" CollectCount="1">
    <CollectFrom>
	  <Mob Name="Scarlet Zealot" Id="1537" />
	  <Mob Name="Scarlet Missionary" Id="1536" />
    </CollectFrom>
    <Hotspots>
      <Hotspot X="1847.026" Y="662.832" Z="41.66972" />
      <Hotspot X="1830.107" Y="625.7269" Z="41.80838" />
      <Hotspot X="1793.754" Y="606.4429" Z="39.81754" />
      <Hotspot X="1760.679" Y="629.6718" Z="41.22786" />
      <Hotspot X="1759.873" Y="670.2471" Z="42.45318" />
      <Hotspot X="1757.487" Y="710.5906" Z="45.34721" />
      <Hotspot X="1767.335" Y="749.0916" Z="52.40147" />
      <Hotspot X="1805.433" Y="762.2025" Z="44.13055" />
      <Hotspot X="1835.925" Y="734.0191" Z="42.46064" />
      <Hotspot X="1836.128" Y="693.3918" Z="41.43217" />
      <Hotspot X="1833.924" Y="651.8715" Z="43.1892" />
    </Hotspots>
  </Objective>
</Quest>
<Quest Id="24993" Name="Annihilate the Worgen">
  <Objective Type="KillMob" MobId="38967" KillCount="5">
    <Hotspots>
      <Hotspot X="2261.795" Y="303.95" Z="33.42439" />
      <Hotspot X="2234.61" Y="274.3753" Z="33.48549" />
      <Hotspot X="2267.244" Y="299.0014" Z="33.69061" />
      <Hotspot X="2289.412" Y="332.9649" Z="33.75133" />
      <Hotspot X="2300.586" Y="372.1768" Z="34.24364" />
      <Hotspot X="2336.507" Y="354.4327" Z="35.11747" />
    </Hotspots>
  </Objective>
</Quest>
<Quest Id="24988" Name="The Chill of Death">
  <Objective Type="CollectItem" ItemId="2876" CollectCount="5">
    <CollectFrom>
	  <Mob Name="Greater Duskbat" Id="1553" />
	  <Mob Name="Vampiric Duskbat" Id="1554" />
    </CollectFrom>
    <Hotspots>
      <Hotspot X="2098.366" Y="73.16331" Z="39.82314" />
      <Hotspot X="2105.673" Y="32.70814" Z="35.97633" />
      <Hotspot X="2099.985" Y="-8.359469" Z="38.69268" />
      <Hotspot X="2096.529" Y="-49.25018" Z="38.75648" />
      <Hotspot X="2129.402" Y="-72.14059" Z="41.90867" />
      <Hotspot X="2163.83" Y="-92.04311" Z="46.65605" />
      <Hotspot X="2198.01" Y="-76.1626" Z="30.06146" />
      <Hotspot X="2201.734" Y="-36.51487" Z="35.67477" />
      <Hotspot X="2196.381" Y="3.526868" Z="38.0244" />
      <Hotspot X="2205.357" Y="42.66727" Z="29.37573" />
      <Hotspot X="2209.438" Y="82.58166" Z="29.6423" />
      <Hotspot X="2186.241" Y="111.3442" Z="46.59664" />
      <Hotspot X="2146.503" Y="105.5983" Z="39.15379" />
      <Hotspot X="2107.923" Y="95.26604" Z="32.4953" />
    </Hotspots>
  </Objective>
</Quest>
<Quest Id="24994" Name="Doom Weed">
  <Objective Type="CollectItem" ItemId="13702" CollectCount="10">
    <CollectFrom>
	<GameObject Name="Gloom Weed" Id="176753" />
    </CollectFrom>
    <Hotspots>
      <Hotspot X="2701.823" Y="421.8867" Z="21.13085" />
      <Hotspot X="2741.872" Y="429.2965" Z="21.54893" />
      <Hotspot X="2779.557" Y="443.0317" Z="20.08649" />
      <Hotspot X="2745.687" Y="463.9856" Z="23.90524" />
      <Hotspot X="2706.219" Y="474.1046" Z="20.72182" />
      <Hotspot X="2673.525" Y="497.6736" Z="15.40251" />
      <Hotspot X="2638.414" Y="517.1526" Z="17.1734" />
      <Hotspot X="2604.524" Y="496.2067" Z="21.20695" />
      <Hotspot X="2613.277" Y="457.368" Z="25.30703" />
      <Hotspot X="2645.297" Y="432.5423" Z="25.65261" />
    </Hotspots>
  </Objective>
</Quest>
<Quest Id="24997" Name="Graverobbers">
  <Objective Type="KillMob" MobId="1941" KillCount="8">
    <Hotspots>
      <Hotspot X="2627.87" Y="535.2071" Z="26.69578" />
      <Hotspot X="2590.842" Y="521.7058" Z="16.57488" />
      <Hotspot X="2580.922" Y="482.368" Z="25.64224" />
      <Hotspot X="2609.408" Y="454.2218" Z="26.92355" />
      <Hotspot X="2648.055" Y="442.6921" Z="21.87049" />
      <Hotspot X="2683.252" Y="423.2625" Z="22.56197" />
      <Hotspot X="2719.85" Y="406.8192" Z="22.62469" />
      <Hotspot X="2756.712" Y="388.7848" Z="21.76283" />
      <Hotspot X="2779.678" Y="355.4859" Z="22.92602" />
      <Hotspot X="2810.266" Y="327.9757" Z="22.86443" />
      <Hotspot X="2842.28" Y="353.3004" Z="23.83437" />
      <Hotspot X="2845.74" Y="393.8751" Z="21.006" />
      <Hotspot X="2809.246" Y="410.5824" Z="19.15647" />
      <Hotspot X="2776.957" Y="434.625" Z="19.17906" />
      <Hotspot X="2737.829" Y="443.8312" Z="21.86992" />
      <Hotspot X="2697.277" Y="446.601" Z="19.18461" />
      <Hotspot X="2669.124" Y="475.4662" Z="15.15213" />
    </Hotspots>
  </Objective>
  <Objective Type="KillMob" MobId="1675" KillCount="5">
    <Hotspots>
      <Hotspot X="2627.87" Y="535.2071" Z="26.69578" />
      <Hotspot X="2590.842" Y="521.7058" Z="16.57488" />
      <Hotspot X="2580.922" Y="482.368" Z="25.64224" />
      <Hotspot X="2609.408" Y="454.2218" Z="26.92355" />
      <Hotspot X="2648.055" Y="442.6921" Z="21.87049" />
      <Hotspot X="2683.252" Y="423.2625" Z="22.56197" />
      <Hotspot X="2719.85" Y="406.8192" Z="22.62469" />
      <Hotspot X="2756.712" Y="388.7848" Z="21.76283" />
      <Hotspot X="2779.678" Y="355.4859" Z="22.92602" />
      <Hotspot X="2810.266" Y="327.9757" Z="22.86443" />
      <Hotspot X="2842.28" Y="353.3004" Z="23.83437" />
      <Hotspot X="2845.74" Y="393.8751" Z="21.006" />
      <Hotspot X="2809.246" Y="410.5824" Z="19.15647" />
      <Hotspot X="2776.957" Y="434.625" Z="19.17906" />
      <Hotspot X="2737.829" Y="443.8312" Z="21.86992" />
      <Hotspot X="2697.277" Y="446.601" Z="19.18461" />
      <Hotspot X="2669.124" Y="475.4662" Z="15.15213" />
    </Hotspots>
  </Objective>
  <Objective Type="CollectItem" ItemId="2834" CollectCount="6">
    <CollectFrom>
	  <Mob Name="Rot Hide Gnoll" Id="1674" />
    </CollectFrom>
    <Hotspots>
      <Hotspot X="2627.87" Y="535.2071" Z="26.69578" />
      <Hotspot X="2590.842" Y="521.7058" Z="16.57488" />
      <Hotspot X="2580.922" Y="482.368" Z="25.64224" />
      <Hotspot X="2609.408" Y="454.2218" Z="26.92355" />
      <Hotspot X="2648.055" Y="442.6921" Z="21.87049" />
      <Hotspot X="2683.252" Y="423.2625" Z="22.56197" />
      <Hotspot X="2719.85" Y="406.8192" Z="22.62469" />
      <Hotspot X="2756.712" Y="388.7848" Z="21.76283" />
      <Hotspot X="2779.678" Y="355.4859" Z="22.92602" />
      <Hotspot X="2810.266" Y="327.9757" Z="22.86443" />
      <Hotspot X="2842.28" Y="353.3004" Z="23.83437" />
      <Hotspot X="2845.74" Y="393.8751" Z="21.006" />
      <Hotspot X="2809.246" Y="410.5824" Z="19.15647" />
      <Hotspot X="2776.957" Y="434.625" Z="19.17906" />
      <Hotspot X="2737.829" Y="443.8312" Z="21.86992" />
      <Hotspot X="2697.277" Y="446.601" Z="19.18461" />
      <Hotspot X="2669.124" Y="475.4662" Z="15.15213" />
    </Hotspots>
  </Objective>
</Quest>
<Quest Id="24998" Name="Maggot Eye">
  <Objective Type="CollectItem" ItemId="3635" CollectCount="1">
    <CollectFrom>
	  <Mob Name="Maggot Eye" Id="1753" />
    </CollectFrom>
    <Hotspots>
      <Hotspot X="2910.7" Y="382.5467" Z="31.48429" />
    </Hotspots>
  </Objective>
</Quest>
<Quest Id="24995" Name="Off the Scales">
  <Objective Type="CollectItem" ItemId="2859" CollectCount="5">
    <CollectFrom>
	  <Mob Name="Vile Fin Puddlejumper" Id="1543" />
	  <Mob Name="Vile Fin Minor Oracle" Id="1544" />
    </CollectFrom>
    <Hotspots>
      <Hotspot X="2918.385" Y="293.2745" Z="21.42081" />
      <Hotspot X="2953.363" Y="309.7706" Z="7.921046" />
      <Hotspot X="2961.11" Y="349.7635" Z="7.966943" />
      <Hotspot X="2978.316" Y="313.0469" Z="5.290102" />
      <Hotspot X="2974.536" Y="272.7469" Z="4.499708" />
      <Hotspot X="2954.426" Y="238.1045" Z="7.199339" />
      <Hotspot X="2941.872" Y="199.996" Z="4.31723" />
      <Hotspot X="2936.441" Y="159.1508" Z="5.418839" />
      <Hotspot X="2896.463" Y="163.1031" Z="7.537606" />
      <Hotspot X="2900.361" Y="203.4531" Z="7.900826" />
      <Hotspot X="2908.867" Y="242.7688" Z="14.32879" />
    </Hotspots>
  </Objective>
</Quest>
<Quest Id="25003" Name="The Family Crypt">
  <Objective Type="KillMob" MobId="1534" KillCount="5">
    <Hotspots>
      <Hotspot X="2958.688" Y="582.4532" Z="92.23306" />
      <Hotspot X="2974.275" Y="620.2407" Z="93.83673" />
      <Hotspot X="2992.477" Y="656.1687" Z="94.13012" />
      <Hotspot X="2995.992" Y="696.5554" Z="92.63119" />
      <Hotspot X="2971.181" Y="728.2621" Z="101.4748" />
      <Hotspot X="2931.162" Y="731.4344" Z="104.7285" />
      <Hotspot X="2898.87" Y="707.7807" Z="115.6837" />
      <Hotspot X="2898.814" Y="667.6875" Z="114.3172" />
      <Hotspot X="2928.789" Y="640.7672" Z="104.9346" />
    </Hotspots>
  </Objective>
  <Objective Type="KillMob" MobId="1530" KillCount="5">
    <Hotspots>
      <Hotspot X="2958.688" Y="582.4532" Z="92.23306" />
      <Hotspot X="2974.275" Y="620.2407" Z="93.83673" />
      <Hotspot X="2992.477" Y="656.1687" Z="94.13012" />
      <Hotspot X="2995.992" Y="696.5554" Z="92.63119" />
      <Hotspot X="2971.181" Y="728.2621" Z="101.4748" />
      <Hotspot X="2931.162" Y="731.4344" Z="104.7285" />
      <Hotspot X="2898.87" Y="707.7807" Z="115.6837" />
      <Hotspot X="2898.814" Y="667.6875" Z="114.3172" />
      <Hotspot X="2928.789" Y="640.7672" Z="104.9346" />
    </Hotspots>
  </Objective>
</Quest>
<Quest Id="25029" Name="Deaths in the Family">
  <Objective Type="CollectItem" ItemId="2830" CollectCount="1">
    <CollectFrom>
	  <Mob Name="Thurman Agamand" Id="1656" />
    </CollectFrom>
    <Hotspots>
      <Hotspot X="2926.814" Y="956.778" Z="122.2828" />
    </Hotspots>
  </Objective>
  <Objective Type="CollectItem" ItemId="2829" CollectCount="1">
    <CollectFrom>
	  <Mob Name="Gregor Agamand" Id="1654" />
    </CollectFrom>
    <Hotspots>
      <Hotspot X="2947.513" Y="971.8582" Z="121.6944" />
    </Hotspots>
  </Objective>
  <Objective Type="CollectItem" ItemId="2828" CollectCount="1">
    <CollectFrom>
	  <Mob Name="Nissa Agamand" Id="1655" />
    </CollectFrom>
    <Hotspots>
      <Hotspot X="2752.172" Y="803.0135" Z="114.2634" />
    </Hotspots>
  </Objective>
  <Objective Type="CollectItem" ItemId="2831" CollectCount="1">
    <CollectFrom>
	  <Mob Name="Devlin Agamand" Id="1657" />
    </CollectFrom>
    <Hotspots>
      <Hotspot X="2812.412" Y="826.9912" Z="111.8414" />
    </Hotspots>
  </Objective>
</Quest>
<Quest Id="25004" Name="The Mills Overrun">
  <Objective Type="CollectItem" ItemId="3162" CollectCount="5">
    <CollectFrom>
	  <Mob Name="Cracked Skull Soldier" Id="1523" />
    </CollectFrom>
    <Hotspots>
      <Hotspot X="2701.348" Y="922.8562" Z="112.7149" />
      <Hotspot X="2682.524" Y="887.2832" Z="109.8066" />
      <Hotspot X="2696.972" Y="848.3102" Z="111.8071" />
      <Hotspot X="2728.137" Y="822.4921" Z="111.944" />
      <Hotspot X="2767.307" Y="811.2311" Z="112.8788" />
      <Hotspot X="2800.626" Y="788.65" Z="114.9486" />
      <Hotspot X="2836.642" Y="769.5346" Z="117.0051" />
      <Hotspot X="2865.609" Y="797.5896" Z="118.3129" />
      <Hotspot X="2893.675" Y="827.0178" Z="111.6792" />
      <Hotspot X="2925.268" Y="852.1127" Z="110.939" />
      <Hotspot X="2893.7" Y="875.6786" Z="118.5671" />
      <Hotspot X="2855.642" Y="889.4228" Z="114.6818" />
      <Hotspot X="2824.542" Y="863.399" Z="111.8417" />
    </Hotspots>
  </Objective>
  <Objective Type="CollectItem" ItemId="3163" CollectCount="3">
    <CollectFrom>
	  <Mob Name="Darkeye Bonecaster" Id="1522" />
    </CollectFrom>
    <Hotspots>
      <Hotspot X="2701.348" Y="922.8562" Z="112.7149" />
      <Hotspot X="2682.524" Y="887.2832" Z="109.8066" />
      <Hotspot X="2696.972" Y="848.3102" Z="111.8071" />
      <Hotspot X="2728.137" Y="822.4921" Z="111.944" />
      <Hotspot X="2767.307" Y="811.2311" Z="112.8788" />
      <Hotspot X="2800.626" Y="788.65" Z="114.9486" />
      <Hotspot X="2836.642" Y="769.5346" Z="117.0051" />
      <Hotspot X="2865.609" Y="797.5896" Z="118.3129" />
      <Hotspot X="2893.675" Y="827.0178" Z="111.6792" />
      <Hotspot X="2925.268" Y="852.1127" Z="110.939" />
      <Hotspot X="2893.7" Y="875.6786" Z="118.5671" />
      <Hotspot X="2855.642" Y="889.4228" Z="114.6818" />
      <Hotspot X="2824.542" Y="863.399" Z="111.8417" />
    </Hotspots>
  </Objective>
</Quest>
<Quest Id="25056" Name="Grisly Grizzlies">
  <Objective Type="CollectItem" ItemId="52270" CollectCount="5">
    <CollectFrom>
	  <Mob Name="Plagued Bruin" Id="39049" />
    </CollectFrom>
    <Hotspots>
      <Hotspot X="1692.724" Y="-665.9852" Z="46.57721" />
      <Hotspot X="1680.201" Y="-627.3678" Z="43.58279" />
      <Hotspot X="1676.351" Y="-587.3668" Z="41.60253" />
      <Hotspot X="1676.887" Y="-547.1837" Z="42.0491" />
      <Hotspot X="1675.095" Y="-505.9167" Z="44.15951" />
      <Hotspot X="1675.45" Y="-465.2738" Z="44.99785" />
      <Hotspot X="1695.332" Y="-430.4658" Z="40.89589" />
      <Hotspot X="1734.435" Y="-425.7182" Z="33.24025" />
      <Hotspot X="1773.19" Y="-436.0542" Z="33.33245" />
      <Hotspot X="1813.971" Y="-439.7881" Z="34.35026" />
      <Hotspot X="1846.309" Y="-464.7462" Z="35.40719" />
      <Hotspot X="1863.137" Y="-500.9841" Z="41.14666" />
      <Hotspot X="1873.886" Y="-539.6767" Z="41.16613" />
      <Hotspot X="1846.55" Y="-569.9399" Z="39.5813" />
      <Hotspot X="1806.552" Y="-566.7399" Z="38.79691" />
      <Hotspot X="1765.034" Y="-565.5711" Z="40.20821" />
    </Hotspots>
  </Objective>
</Quest>
<Quest Id="25009" Name="At War With The Scarlet Crusade">
  <Objective Type="KillMob" MobId="1537" KillCount="3">
    <Hotspots>
      <Hotspot X="2120.868" Y="-567.9372" Z="71.1736" />
      <Hotspot X="2157.752" Y="-583.1252" Z="79.3903" />
      <Hotspot X="2193.021" Y="-563.6572" Z="79.75726" />
      <Hotspot X="2186.709" Y="-523.0408" Z="79.46124" />
      <Hotspot X="2175.908" Y="-483.8297" Z="77.24616" />
      <Hotspot X="2155.008" Y="-449.9955" Z="71.05366" />
    </Hotspots>
  </Objective>
  <Objective Type="KillMob" MobId="1538" KillCount="4">
    <Hotspots>
      <Hotspot X="2120.868" Y="-567.9372" Z="71.1736" />
      <Hotspot X="2157.752" Y="-583.1252" Z="79.3903" />
      <Hotspot X="2193.021" Y="-563.6572" Z="79.75726" />
      <Hotspot X="2186.709" Y="-523.0408" Z="79.46124" />
      <Hotspot X="2175.908" Y="-483.8297" Z="77.24616" />
      <Hotspot X="2155.008" Y="-449.9955" Z="71.05366" />
    </Hotspots>
  </Objective>
</Quest>
<Quest Id="25013" Name="A Little Oomph">
  <Objective Type="CollectItem" ItemId="2872" CollectCount="4">
    <CollectFrom>
	  <Mob Name="Vicious Night Web Spider" Id="1555" />
    </CollectFrom>
    <Hotspots>
      <Hotspot X="2150.856" Y="-721.0369" Z="67.91755" />
      <Hotspot X="2161.687" Y="-759.2839" Z="73.14724" />
      <Hotspot X="2183.313" Y="-792.9758" Z="78.14039" />
      <Hotspot X="2196.836" Y="-830.5841" Z="81.48038" />
      <Hotspot X="2187.813" Y="-870.2002" Z="85.263" />
      <Hotspot X="2215.173" Y="-899.1322" Z="80.05077" />
      <Hotspot X="2243.992" Y="-926.9366" Z="75.8258" />
      <Hotspot X="2267.035" Y="-959.8155" Z="77.64922" />
      <Hotspot X="2295.609" Y="-988.0107" Z="77.09229" />
      <Hotspot X="2325.511" Y="-960.6434" Z="74.61227" />
      <Hotspot X="2330.604" Y="-920.704" Z="72.70995" />
      <Hotspot X="2323.765" Y="-880.1312" Z="74.09361" />
      <Hotspot X="2300.11" Y="-846.4554" Z="73.36189" />
      <Hotspot X="2269.93" Y="-819.8662" Z="70.77" />
      <Hotspot X="2239.537" Y="-793.2437" Z="74.77374" />
      <Hotspot X="2202.716" Y="-775.1985" Z="76.56338" />
    </Hotspots>
  </Objective>
</Quest>










<!-- ################################### End of Quest Overrides #################################################################### -->
<QuestOrder IgnoreCheckPoints="False" >
<If Condition="Me.IsAlliance" >
  <CustomBehavior File="LoadProfile" ProfileName="Next[Cava]" />
</If>
<If Condition="Me.ZoneId != 85">
  <If Condition="Me.ZoneId != 1637">
    <CustomBehavior File="LoadProfile" ProfileName="MovetoMainCity[Cava]" />
  <Else>
    <RunTo X="1803.344" Y="-4370.224" Z="102.8182" />
    <RunTo X="1846.624" Y="-4397.398" Z="135.215" />
    <CustomBehavior File="UseTransport" TransportId="164871"
      WaitAtX="1840.128" WaitAtY="-4390.435" WaitAtZ="135.2329"
      GetOffX="2067.576" GetOffY="290.3322" GetOffZ="97.03136"
      StandOnX="1835.073" StandOnY="-4385.413" StandOnZ="135.0524"
      TransportStartX="1833.509" TransportStartY="-4391.543" TransportStartZ="152.7679"
      TransportEndX="2062.376" TransportEndY="292.998" TransportEndZ="114.973"/>
    <RunTo X="2222.609" Y="1014.027" Z="37.12219" />
    </Else>
  </If>
</If>
<If Condition="Me.LevelFraction &gt;= 11.30">
  <CustomBehavior File="LoadProfile" ProfileName="Next[Cava]" />
</If>
<If Condition="Me.ZoneId != 85">
  <CustomBehavior File="UserDialog" AllowBotStop="True" SoundCue="Exclamation" SoundCueInterval="1"
  Text="There is a problem moving char to quest\n\n
  Please move your char to: TIRISFAL GLADES\n
  and start bot." />
</If>
<CustomBehavior File="Message" Text="Compiling Tirisfal Glades Quests (05-11)" LogColor="Aquamarine" />
<!--# # # Level 5 # # # -->
<If Condition="!HasQuest(24978) &amp;&amp; !IsQuestCompleted(24978)" >
  <CustomBehavior File="ForceSetVendor" DoSell="True" DoRepair="True" />
  <CustomBehavior File="UserSettings" DrinkAmount="0" FoodAmount="0" />
  <CustomBehavior File="InteractWith" NonCompeteDistance="0" KeepTargetSelected="True" MobId="10666" WaitTime="1000" CollectionDistance="50" X="2240.748" Y="1022.179" Z="36.49952" />
  <CustomBehavior File="InteractWith" NonCompeteDistance="0" KeepTargetSelected="True" MobId="10666" WaitTime="1000" CollectionDistance="50" X="2240.748" Y="1022.179" Z="36.49952" />
  <CustomBehavior File="WaitTimer" WaitTime="1000" />
  <CustomBehavior File="RunMacro" Macro="/run for i=0,4 do for j=1,GetContainerNumSlots(i)do l=GetContainerItemLink(i,j)if l then _,_,q=GetItemInfo(l)if q==0 or q==2 or q==3 then PickupContainerItem(i,j)PickupMerchantItem(0)end end end end" />
  <CustomBehavior File="WaitTimer" WaitTime="1000" />
  <CustomBehavior File="RunMacro" Macro="/run for i=0,4 do for j=1,GetContainerNumSlots(i)do l=GetContainerItemLink(i,j)if l then _,_,q=GetItemInfo(l)if q==0 or q==2 or q==3 then PickupContainerItem(i,j)DeleteCursorItem()end end end end" />
  <CustomBehavior File="UserSettings" DrinkAmount="20" FoodAmount="20" />
</If>
<CustomBehavior File="UserSettings" DrinkAmount="20" FoodAmount="20"/>
<PickUp QuestName="Reaping the Reapers" QuestId="24978" GiverName="Deathguard Simmer" GiverId="1519" X="2220.611" Y="1011.286" Z="37.12373" />
<PickUp QuestName="Fields of Grief" QuestId="24975" GiverName="Apothecary Johaan" GiverId="1518" X="2217.135" Y="1017.366" Z="37.12373" />
<!--
<PickUp QuestName="Ever So Lonely" QuestId="24974" GiverName="Sedrick Calston" GiverId="38925" X="2221.394" Y="1011.333" Z="45.25862" />
-->
<Objective QuestName="Fields of Grief" QuestId="24975" Type="CollectItem" ItemId="2846" CollectCount="10" />
<Objective QuestName="Reaping the Reapers" QuestId="24978" Type="KillMob" MobId="1934" KillCount="10" />
<!--
<If Condition="HasQuest(24974) &amp;&amp; !IsQuestCompleted(24974)">
  <While Condition="!IsObjectiveComplete(1, 24974)">
    <CustomBehavior File="CombatUseItemOnV2" MobId1="1543" MobId2="1544" ItemId="52059" UseWhenMobHasHealthPercent="30"
      ItemAppliesAuraId="AssumeItemUseAlwaysSucceeds" RecallPetAtMobPercentHealth="40" X="2474.108" Y="1450.953" Z="11.28125" />
  </While>
</If>
-->
<TurnIn QuestName="Reaping the Reapers" QuestId="24978" TurnInName="Deathguard Simmer" TurnInId="1519" X="2220.611" Y="1011.286" Z="37.12373" />
<PickUp QuestName="The Scarlet Palisade" QuestId="24980" GiverName="Deathguard Simmer" GiverId="1519" />
<TurnIn QuestName="Fields of Grief" QuestId="24975" TurnInName="Apothecary Johaan" TurnInId="1518" X="2217.135" Y="1017.366" Z="37.12373" />
<PickUp QuestName="Variety is the Spice of Death" QuestId="24976" GiverName="Apothecary Johaan" GiverId="1518" X="2217.135" Y="1017.366" Z="37.12373" />
<If Condition="HasQuest(24976) &amp;&amp; !IsQuestCompleted(24976)">
  <CustomBehavior File="InteractWith" QuestId="24976" QuestObjectiveIndex="1" MobId="202422" NumOfTimes="1000" NonCompeteDistance="0" CollectionDistance="1000" >
    <HuntingGrounds>
      <Hotspot X="2158.006" Y="831.394" Z="30.59422" />
      <Hotspot X="2144.956" Y="792.9863" Z="30.37889" />
      <Hotspot X="2181.522" Y="776.7186" Z="30.69724" />
      <Hotspot X="2221.188" Y="784.9879" Z="30.69728" />
      <Hotspot X="2243.342" Y="818.3333" Z="30.69731" />
      <Hotspot X="2205.054" Y="831.7079" Z="30.69724" />
    </HuntingGrounds>
  </CustomBehavior>
<!--
<Objective QuestName="Variety is the Spice of Death" QuestId="24976" Type="CollectItem" ItemId="52067" CollectCount="4" />
-->
  <Objective QuestName="Variety is the Spice of Death" QuestId="24976" Type="CollectItem" ItemId="52066" CollectCount="4" />
  <CustomBehavior File="InteractWith" QuestId="24976" QuestObjectiveIndex="3" MobId="38933" NumOfTimes="1000" InteractByLooting="True" NonCompeteDistance="0" CollectionDistance="1000" >
    <HuntingGrounds>
      <Hotspot X="2572.227" Y="1464.295" Z="-4.508661" />
      <Hotspot X="2605.931" Y="1442.583" Z="-5.103283" />
      <Hotspot X="2636.316" Y="1469.144" Z="-6.525883" />
      <Hotspot X="2619.359" Y="1505.458" Z="-7.216598" />
      <Hotspot X="2584.579" Y="1525.971" Z="-8.101376" />
      <Hotspot X="2570.129" Y="1488.099" Z="-7.015973" />
    </HuntingGrounds>
  </CustomBehavior>
<!--
<Objective QuestName="Variety is the Spice of Death" QuestId="24976" Type="CollectItem" ItemId="52068" CollectCount="8" />
-->
</If>
<!--
<If Condition="!HasQuest(24979) &amp;&amp; !IsQuestCompleted(24979) &amp;&amp; !HasItem(52079)">
  <LootMobs Value="true" />
  <SetGrindArea>
    <GrindArea>
	<Factions>67</Factions>
    <Hotspots>
      <Hotspot X="2384.22" Y="1409.315" Z="34.44831" />
      <Hotspot X="2387.65" Y="1449.644" Z="34.43085" />
      <Hotspot X="2389.879" Y="1489.681" Z="33.70216" />
      <Hotspot X="2407.781" Y="1527.05" Z="32.55365" />
      <Hotspot X="2416.097" Y="1566.771" Z="32.60154" />
      <Hotspot X="2396.632" Y="1602.792" Z="33.51886" />
      <Hotspot X="2356.469" Y="1600.489" Z="35.57378" />
      <Hotspot X="2350.626" Y="1560.786" Z="34.33483" />
      <Hotspot X="2368.409" Y="1524.57" Z="36.35016" />
    </Hotspots>
  </GrindArea>
  </SetGrindArea>
  <GrindTo Condition="HasItem(52079)" />
  <LootMobs Value="null" />
</If>
<If Condition="!HasQuest(24979) &amp;&amp; !IsQuestCompleted(24979) &amp;&amp; HasItem(52079)">
  <PickUp QuestName="A Scarlet Letter" QuestId="24979" GiverType="Item" GiverId="52079" />
</If>
<If Condition="HasQuest(24979) &amp;&amp; !IsQuestCompleted(24979)">
  <While Condition="!IsQuestCompleted(24979)">
    <RunTo X="2441.099" Y="1597.97" Z="72.15547" />
    <CustomBehavior File="InteractWith" QuestId="24979" MobId="38999" NonCompeteDistance="0" WaitForNpcs="False" InteractByGossipOptions="1,1,1" X="2441.099" Y="1597.97" Z="72.15547" />
  </While>
</If>
-->
<Objective QuestName="The Scarlet Palisade" QuestId="24980" Type="KillMob" MobId="1535" KillCount="10" />
<!--
<TurnIn QuestName="A Scarlet Letter" QuestId="24979" TurnInName="Deathguard Simmer" TurnInId="1519" X="2220.611" Y="1011.286" Z="37.12373" />
-->
<TurnIn QuestName="The Scarlet Palisade" QuestId="24980" TurnInName="Deathguard Simmer" TurnInId="1519" X="2220.611" Y="1011.286" Z="37.12373" />
<TurnIn QuestName="Variety is the Spice of Death" QuestId="24976" TurnInName="Apothecary Johaan" TurnInId="1518" X="2217.135" Y="1017.366" Z="37.12373" />
<PickUp QuestName="Johaan's Experiment" QuestId="24977" GiverName="Apothecary Johaan" GiverId="1518" X="2217.135" Y="1017.366" Z="37.12373" />
<TurnIn QuestName="Johaan's Experiment" QuestId="24977" TurnInName="Captured Scarlet Zealot" TurnInId="1931" X="2252.24" Y="1013.35" Z="36.47287" />
<PickUp QuestName="Gordo's Task" QuestId="25038" GiverName="Gordo" GiverId="10666" X="2240.053" Y="1024.575" Z="36.45156" />
<Objective QuestName="Gordo's Task" QuestId="25038" Type="CollectItem" ItemId="12737" CollectCount="3" />
<PickUp QuestName="A Putrid Task" QuestId="25090" GiverName="Deathguard Dillinger" GiverId="1496" X="2186.042" Y="658.8768" Z="32.98425" />
<PickUp QuestName="The New Forsaken" QuestId="24982" GiverName="Deathguard Dillinger" GiverId="1496" X="2186.042" Y="658.8768" Z="32.98425" />
<Objective QuestName="A Putrid Task" QuestId="25090" Type="CollectItem" ItemId="2855" CollectCount="7" />
<If Condition="HasQuest(25090)" >
  <RunTo X="2260.998" Y="287.5288" Z="33.3798" />
  <CustomBehavior File="ForceSetVendor" DoMail="True" DoSell="True" DoRepair="True" />
  <CustomBehavior File="InteractWith" NonCompeteDistance="0" KeepTargetSelected="True" MobId="2137" WaitTime="1000" X="2302.86" Y="288.523" Z="33.3571" />
  <CustomBehavior File="InteractWith" NonCompeteDistance="0" KeepTargetSelected="True" MobId="2137" WaitTime="1000" X="2302.86" Y="288.523" Z="33.3571" />
  <CustomBehavior File="WaitTimer" WaitTime="1000" />
  <CustomBehavior File="RunMacro" Macro="/run for i=0,4 do for j=1,GetContainerNumSlots(i)do l=GetContainerItemLink(i,j)if l then _,_,q=GetItemInfo(l)if q==0 or q==2 or q==3 then PickupContainerItem(i,j)PickupMerchantItem(0)end end end end" />
  <If Condition="Me.FreeBagSlots &lt; 40 &amp;&amp; Me.Silver &gt;= 5" >
    <CustomBehavior File="InteractWith" NonCompeteDistance="0" MobId="2134" BuyItemId="4496" WaitTime="5000" CollectionDistance="50" InteractByQuestFrameDisposition="TerminateBehavior" X="2305.479" Y="288.0078" Z="33.35704" />
  </If>
  <If Condition="Me.FreeBagSlots &lt; 40 &amp;&amp; Me.Silver &gt;= 5" >
    <CustomBehavior File="InteractWith" NonCompeteDistance="0" MobId="2134" BuyItemId="4496" WaitTime="5000" CollectionDistance="50" InteractByQuestFrameDisposition="TerminateBehavior" X="2305.479" Y="288.0078" Z="33.35704" />
  </If>
  <CustomBehavior File="Cava\SetHearthstone" MobId="5688" X="2285.95" Y="282.613" Z="33.24683" />
</If>
<TurnIn QuestName="A Putrid Task" QuestId="25090" TurnInName="Deathguard Dillinger" TurnInId="1496" X="2186.042" Y="658.8768" Z="32.98425" />
<TurnIn QuestName="Gordo's Task" QuestId="25038" TurnInName="Junior Apothecary Holland" TurnInId="10665" X="2250.269" Y="316.375" Z="34.81486" />
<PickUp QuestName="Darkhound Pounding" QuestId="24990" GiverName="Junior Apothecary Holland" GiverId="10665" X="2250.269" Y="316.375" Z="34.81486" />
<PickUp QuestName="A Thorn in our Side" QuestId="24981" GiverName="Executor Zygand" GiverId="1515" X="2275.082" Y="297.6129" Z="33.64952" />
<TurnIn QuestName="The New Forsaken" QuestId="24982" TurnInName="Magistrate Sevren" TurnInId="1499" X="2315.887" Y="278.1732" Z="44.97721" />
<If Condition="!HasQuest(24983) &amp;&amp; !IsQuestCompleted(24983)">
  <PickUp QuestName="Forsaken Duties" QuestId="24983" GiverName="Magistrate Sevren" GiverId="1499" X="2315.887" Y="278.1732" Z="44.97721" />
  <RunTo X="2302.5" Y="279.1147" Z="44.42836" />
  <CustomBehavior File="MyCTM" X="2278.517" Y="284.3423" Z="33.82134" />
</If>
<Objective QuestName="Darkhound Pounding" QuestId="24990" Type="CollectItem" ItemId="2858" CollectCount="5" />
<If Condition="!HasQuest(24992) &amp;&amp; !IsQuestCompleted(24992)">
  <SetGrindArea>
    <GrindArea>
	<Factions>38</Factions>
    <Hotspots>
      <Hotspot X="2187.673" Y="313.7323" Z="35.65869" />
      <Hotspot X="2181.305" Y="353.7985" Z="42.85993" />
      <Hotspot X="2157.185" Y="385.4195" Z="50.10912" />
      <Hotspot X="2119.765" Y="399.8929" Z="53.63862" />
      <Hotspot X="2085.056" Y="420.2378" Z="58.27397" />
      <Hotspot X="2048.016" Y="436.0151" Z="48.04784" />
      <Hotspot X="2018.924" Y="463.3003" Z="40.28649" />
      <Hotspot X="1996.334" Y="496.5455" Z="36.81657" />
      <Hotspot X="1970.679" Y="527.4138" Z="42.07484" />
      <Hotspot X="1941.554" Y="554.2789" Z="50.88175" />
      <Hotspot X="1904.798" Y="569.9554" Z="47.2686" />
      <Hotspot X="1869.753" Y="551.5902" Z="39.22961" />
      <Hotspot X="1882.041" Y="512.4634" Z="37.4883" />
      <Hotspot X="1900.35" Y="476.6878" Z="37.80049" />
      <Hotspot X="1908.381" Y="435.8369" Z="34.61976" />
      <Hotspot X="1935.369" Y="406.5072" Z="39.72733" />
      <Hotspot X="1966.679" Y="381.345" Z="35.24394" />
      <Hotspot X="2000.168" Y="358.24" Z="40.22854" />
      <Hotspot X="2039.151" Y="372.3969" Z="42.05231" />
      <Hotspot X="2079.552" Y="363.7648" Z="43.24469" />
      <Hotspot X="2113.256" Y="343.2099" Z="50.0988" />
    </Hotspots>
  </GrindArea>
  </SetGrindArea>
  <GrindTo Condition="HasQuest(24992)" />
</If>
<If Condition="HasQuest(24981) &amp;&amp; !IsQuestCompleted(24981 )">
  <Objective QuestName="A Thorn in our Side" QuestId="24981" Type="CollectItem" ItemId="52077" CollectCount="1" />
  <SetGrindArea>
    <GrindArea>
	<Factions>1537</Factions>
    <Hotspots>
      <Hotspot X="1847.026" Y="662.832" Z="41.66972" />
      <Hotspot X="1830.107" Y="625.7269" Z="41.80838" />
      <Hotspot X="1793.754" Y="606.4429" Z="39.81754" />
      <Hotspot X="1760.679" Y="629.6718" Z="41.22786" />
      <Hotspot X="1759.873" Y="670.2471" Z="42.45318" />
      <Hotspot X="1757.487" Y="710.5906" Z="45.34721" />
      <Hotspot X="1767.335" Y="749.0916" Z="52.40147" />
      <Hotspot X="1805.433" Y="762.2025" Z="44.13055" />
      <Hotspot X="1835.925" Y="734.0191" Z="42.46064" />
      <Hotspot X="1836.128" Y="693.3918" Z="41.43217" />
      <Hotspot X="1833.924" Y="651.8715" Z="43.1892" />
    </Hotspots>
  </GrindArea>
  </SetGrindArea>
  <GrindTo Condition="IsObjectiveComplete(1, 24981) || IsObjectiveComplete(2, 24981)" />
  <Objective QuestName="A Thorn in our Side" QuestId="24981" Type="KillMob" MobId="1537" KillCount="3" />
  <Objective QuestName="A Thorn in our Side" QuestId="24981" Type="KillMob" MobId="1536" KillCount="3" />
</If>
<TurnIn QuestName="A Thorn in our Side" QuestId="24981" TurnInName="Executor Zygand" TurnInId="1515" X="2275.082" Y="297.6129" Z="33.64952" />
<TurnIn QuestName="Escaped From Gilneas" QuestId="24992" TurnInName="Executor Zygand" TurnInId="1515" X="2275.082" Y="297.6129" Z="33.64952" />
<PickUp QuestName="Annihilate the Worgen" QuestId="24993" GiverName="Executor Zygand" GiverId="1515" X="2275.082" Y="297.6129" Z="33.64952" />
<TurnIn QuestName="Darkhound Pounding" QuestId="24990" TurnInName="Junior Apothecary Holland" TurnInId="10665" X="2250.269" Y="316.375" Z="34.81486" />
<PickUp QuestName="Holland's Experiment" QuestId="24996" GiverName="Junior Apothecary Holland" GiverId="10665" X="2250.269" Y="316.375" Z="34.81486" />
<If Condition="HasQuest(24996)">
  <TurnIn QuestName="Holland's Experiment" QuestId="24996" TurnInName="Captured Mountaineer" TurnInId="2211" X="2244.866" Y="320.3351" Z="40.60149" />
  <RunTo X="2253.351" Y="314.9772" Z="41.13781" />
  <CustomBehavior File="MyCTM" X="2265.396" Y="306.608" Z="33.41453" />
</If>
<PickUp QuestName="Garren's Haunt" QuestId="24991" GiverName="Junior Apothecary Holland" GiverId="10665" X="2250.269" Y="316.375" Z="34.81486" />
<Objective QuestName="Annihilate the Worgen" QuestId="24993" Type="KillMob" MobId="38967" KillCount="5" />
<TurnIn QuestName="Annihilate the Worgen" QuestId="24993" TurnInName="Executor Zygand" TurnInId="1515" X="2275.082" Y="297.6129" Z="33.64952" />
<If Condition="HasQuest(24983) &amp;&amp; Me.LevelFraction &gt;= 11.30">
  <CustomBehavior File="Message" Text="Moving to SILVERPINE FOREST, Please do not stop bot" LogColor="Aquamarine" />
  <PickUp QuestName="Warchief's Command: Silverpine Forest!" QuestId="26964" GiverName="Executor Zygand" GiverId="1515" X="2275.082" Y="297.6129" Z="33.64941" />
  <RunTo X="1421.067" Y="1019.964" Z="52.67456" />
  <CustomBehavior File="InteractWith" MobId="44825" MobState="Alive" X="1422.93" Y="1017.771" Z="52.56585" />
  <TurnIn QuestName="Warchief's Command: Silverpine Forest!" QuestId="26964" TurnInName="Grand Executor Mortuus" TurnInId="44615" X="1383" Y="1038.63" Z="54.31712" />
  <CustomBehavior File="LoadProfile" ProfileName="[H-Quest](11-20)SilverpineForest[Cava]" />
</If>
<TurnIn QuestName="Forsaken Duties" QuestId="24983" TurnInName="Deathguard Linnea" TurnInId="1495" X="2022.326" Y="74.04601" Z="36.44639" />
<PickUp QuestName="The Chill of Death" QuestId="24988" GiverName="Gretchen Dedmar" GiverId="1521" X="2017.219" Y="84.95139" Z="36.7408" />
<Objective QuestName="The Chill of Death" QuestId="24988" Type="CollectItem" ItemId="2876" CollectCount="5" />
<TurnIn QuestName="The Chill of Death" QuestId="24988" TurnInName="Gretchen Dedmar" TurnInId="1521" X="2017.219" Y="84.95139" Z="36.7408" />
<PickUp QuestName="Return to the Magistrate" QuestId="24989" GiverName="Deathguard Linnea" GiverId="1495" X="2022.326" Y="74.04601" Z="36.44639" />
<If Condition="HasQuest(24989)">
  <TurnIn QuestName="Return to the Magistrate" QuestId="24989" TurnInName="Magistrate Sevren" TurnInId="1499" X="2315.887" Y="278.1732" Z="44.97721" />
  <RunTo X="2302.5" Y="279.1147" Z="44.42836" />
  <CustomBehavior File="MyCTM" X="2278.517" Y="284.3423" Z="33.82134" />
</If>
<If Condition="HasQuest(24991) &amp;&amp; Me.LevelFraction &gt;= 11.30">
  <CustomBehavior File="Message" Text="Moving to SILVERPINE FOREST, Please do not stop bot" LogColor="Aquamarine" />
  <PickUp QuestName="Warchief's Command: Silverpine Forest!" QuestId="26964" GiverName="Executor Zygand" GiverId="1515" X="2275.082" Y="297.6129" Z="33.64941" />
  <RunTo X="1421.067" Y="1019.964" Z="52.67456" />
  <CustomBehavior File="InteractWith" MobId="44825" MobState="Alive" X="1422.93" Y="1017.771" Z="52.56585" />
  <TurnIn QuestName="Warchief's Command: Silverpine Forest!" QuestId="26964" TurnInName="Grand Executor Mortuus" TurnInId="44615" X="1383" Y="1038.63" Z="54.31712" />
  <CustomBehavior File="LoadProfile" ProfileName="[H-Quest](11-20)SilverpineForest[Cava]" />
</If>
<TurnIn QuestName="Garren's Haunt" QuestId="24991" TurnInName="Apothecary Jerrod" TurnInId="38977" X="2796.415" Y="247.5156" Z="32.23903" />
<PickUp QuestName="Doom Weed" QuestId="24994" GiverName="Apothecary Jerrod" GiverId="38977" X="2796.415" Y="247.5156" Z="32.23903" />
<PickUp QuestName="Graverobbers" QuestId="24997" GiverName="Apprentice Crispin" GiverId="38978" X="2801.549" Y="249.5" Z="31.77237" />
<If Condition="HasQuest(24997) &amp;&amp; !IsQuestCompleted(24997)">
  <LootMobs Value="true" />
</If>
<Objective QuestName="Doom Weed" QuestId="24994" Type="CollectItem" ItemId="13702" CollectCount="10" />
<If Condition="HasQuest(24997)">
  <LootMobs Value="null" />
</If>
<Objective QuestName="Graverobbers" QuestId="24997" Type="CollectItem" ItemId="2834" CollectCount="6" />
<Objective QuestName="Graverobbers" QuestId="24997" Type="KillMob" MobId="1941" KillCount="8" />
<Objective QuestName="Graverobbers" QuestId="24997" Type="KillMob" MobId="1675" KillCount="5" />
<TurnIn QuestName="Doom Weed" QuestId="24994" TurnInName="Apothecary Jerrod" TurnInId="38977" X="2796.415" Y="247.5156" Z="32.23903" />
<PickUp QuestName="Off the Scales" QuestId="24995" GiverName="Apothecary Jerrod" GiverId="38977" X="2796.415" Y="247.5156" Z="32.23903" />
<TurnIn QuestName="Graverobbers" QuestId="24997" TurnInName="Apprentice Crispin" TurnInId="38978" X="2801.549" Y="249.5" Z="31.77237" />
<PickUp QuestName="Maggot Eye" QuestId="24998" GiverName="Apprentice Crispin" GiverId="38978" X="2801.549" Y="249.5" Z="31.77237" />
<PickUp QuestName="Planting the Seed of Fear" QuestId="24999" GiverName="Apprentice Crispin" GiverId="38978" X="2801.549" Y="249.5" Z="31.77237" />
<Objective QuestName="Maggot Eye" QuestId="24998" Type="CollectItem" ItemId="3635" CollectCount="1" />
<Objective QuestName="Off the Scales" QuestId="24995" Type="CollectItem" ItemId="2859" CollectCount="5" />
<If Condition="HasQuest(24999) &amp;&amp; !IsQuestCompleted(24999)">
  <CustomBehavior File="InteractWith" NonCompeteDistance="0" QuestId="24999" MobId="38937" NumOfTimes="1000" MobState="Alive" >
    <HuntingGrounds>
      <Hotspot X="3007.051" Y="358.3804" Z="4.629209" />
      <Hotspot X="3000.272" Y="318.3062" Z="2.805238" />
      <Hotspot X="2990.926" Y="278.8527" Z="2.263273" />
      <Hotspot X="2977.387" Y="240.1494" Z="2.877417" />
      <Hotspot X="2959.703" Y="203.307" Z="1.736035" />
      <Hotspot X="2961.297" Y="163.3872" Z="4.349986" />
      <Hotspot X="2959.338" Y="122.8426" Z="0.7551703" />
      <Hotspot X="2974.066" Y="85.74187" Z="4.261087" />
      <Hotspot X="2981.45" Y="46.43995" Z="1.70788" />
      <Hotspot X="2994.474" Y="7.935196" Z="1.098036" />
    </HuntingGrounds>
  </CustomBehavior>
</If>
<TurnIn QuestName="Maggot Eye" QuestId="24998" TurnInName="Apprentice Crispin" TurnInId="38978" X="2801.549" Y="249.5" Z="31.77237" />
<TurnIn QuestName="Planting the Seed of Fear" QuestId="24999" TurnInName="Apprentice Crispin" TurnInId="38978" X="2801.549" Y="249.5" Z="31.77237" />
<TurnIn QuestName="Off the Scales" QuestId="24995" TurnInName="Apothecary Jerrod" TurnInId="38977" X="2796.415" Y="247.5156" Z="32.23903" />
<PickUp QuestName="Head for the Mills" QuestId="25031" GiverName="Apothecary Jerrod" GiverId="38977" X="2796.415" Y="247.5156" Z="32.23903" />
<TurnIn QuestName="Head for the Mills" QuestId="25031" TurnInName="Coleman Farthing" TurnInId="1500" X="2936.989" Y="566.5" Z="91.44164" />
<PickUp QuestName="The Family Crypt" QuestId="25003" GiverName="Coleman Farthing" GiverId="1500" X="2936.989" Y="566.5" Z="91.44164" />
<If Condition="HasQuest(25003) &amp;&amp; !IsQuestCompleted(25003)">
  <SetGrindArea>
    <GrindArea>
	<Factions>21</Factions>
    <Hotspots>
      <Hotspot X="2958.688" Y="582.4532" Z="92.23306" />
      <Hotspot X="2974.275" Y="620.2407" Z="93.83673" />
      <Hotspot X="2992.477" Y="656.1687" Z="94.13012" />
      <Hotspot X="2995.992" Y="696.5554" Z="92.63119" />
      <Hotspot X="2971.181" Y="728.2621" Z="101.4748" />
      <Hotspot X="2931.162" Y="731.4344" Z="104.7285" />
      <Hotspot X="2898.87" Y="707.7807" Z="115.6837" />
      <Hotspot X="2898.814" Y="667.6875" Z="114.3172" />
      <Hotspot X="2928.789" Y="640.7672" Z="104.9346" />
    </Hotspots>
  </GrindArea>
  </SetGrindArea>
  <GrindTo Condition="IsObjectiveComplete(1, 25003) || IsObjectiveComplete(2, 25003)" />
  <Objective QuestName="The Family Crypt" QuestId="25003" Type="KillMob" MobId="1534" KillCount="5" />
  <Objective QuestName="The Family Crypt" QuestId="25003" Type="KillMob" MobId="1530" KillCount="5" />
</If>
<TurnIn QuestName="The Family Crypt" QuestId="25003" TurnInName="Coleman Farthing" TurnInId="1500" X="2936.989" Y="566.5" Z="91.44164" />
<PickUp QuestName="The Mills Overrun" QuestId="25004" GiverName="Coleman Farthing" GiverId="1500" X="2936.989" Y="566.5" Z="91.44164" />
<PickUp QuestName="Deaths in the Family" QuestId="25029" GiverName="Coleman Farthing" GiverId="1500" X="2936.989" Y="566.5" Z="91.44164" />
<If Condition="HasQuest(25004) &amp;&amp; !IsQuestCompleted(25004)">
  <LootMobs Value="true" />
</If>
<Objective QuestName="Deaths in the Family" QuestId="25029" Type="CollectItem" ItemId="2830" CollectCount="1" />
<Objective QuestName="Deaths in the Family" QuestId="25029" Type="CollectItem" ItemId="2829" CollectCount="1" />
<Objective QuestName="Deaths in the Family" QuestId="25029" Type="CollectItem" ItemId="2828" CollectCount="1" />
<Objective QuestName="Deaths in the Family" QuestId="25029" Type="CollectItem" ItemId="2831" CollectCount="1" />
<Objective QuestName="The Mills Overrun" QuestId="25004" Type="CollectItem" ItemId="3162" CollectCount="5" />
<If Condition="HasQuest(25004)">
  <LootMobs Value="null" />
</If>
<Objective QuestName="The Mills Overrun" QuestId="25004" Type="CollectItem" ItemId="3163" CollectCount="3" />
<TurnIn QuestName="The Mills Overrun" QuestId="25004" TurnInName="Coleman Farthing" TurnInId="1500" X="2936.989" Y="566.5" Z="91.44164" />
<TurnIn QuestName="Deaths in the Family" QuestId="25029" TurnInName="Coleman Farthing" TurnInId="1500" X="2936.989" Y="566.5" Z="91.44164" />
<PickUp QuestName="Speak with Sevren" QuestId="25005" GiverName="Coleman Farthing" GiverId="1500" X="2936.989" Y="566.5" Z="91.44164" />
<If Condition="HasQuest(25005)">
  <CustomBehavior File="Cava\GoSavedInn" BindPointAreaId="159" />
</If>
<TurnIn QuestName="Speak with Sevren" QuestId="25005" TurnInName="Magistrate Sevren" TurnInId="1499" X="2315.887" Y="278.1732" Z="44.97721" />
<If Condition="!HasQuest(25006) &amp;&amp; !IsQuestCompleted(25006)">
  <PickUp QuestName="The Grasp Weakens" QuestId="25006" GiverName="Magistrate Sevren" GiverId="1499" X="2315.887" Y="278.1732" Z="44.97721" />
  <RunTo X="2302.5" Y="279.1147" Z="44.42836" />
  <CustomBehavior File="MyCTM" X="2278.517" Y="284.3423" Z="33.82134" />
</If>
<If Condition="!HasQuest(26964) &amp;&amp; !IsQuestCompleted(26964) &amp;&amp; Me.LevelFraction &gt;= 11.30">
  <CustomBehavior File="Message" Text="Moving to SILVERPINE FOREST, Please do not stop bot" LogColor="Aquamarine" />
  <PickUp QuestName="Warchief's Command: Silverpine Forest!" QuestId="26964" GiverName="Executor Zygand" GiverId="1515" X="2275.082" Y="297.6129" Z="33.64941" />
  <RunTo X="1421.067" Y="1019.964" Z="52.67456" />
  <CustomBehavior File="InteractWith" MobId="44825" MobState="Alive" X="1422.93" Y="1017.771" Z="52.56585" />
  <TurnIn QuestName="Warchief's Command: Silverpine Forest!" QuestId="26964" TurnInName="Grand Executor Mortuus" TurnInId="44615" X="1383" Y="1038.63" Z="54.31712" />
  <CustomBehavior File="LoadProfile" ProfileName="[H-Quest](11-20)SilverpineForest[Cava]" />
</If>
<If Condition="HasQuest(25006) &amp;&amp; !IsQuestCompleted(25006)">
  <While Condition="!IsQuestCompleted(25006)">
    <CustomBehavior File="InteractWith" QuestId="25006" MobId="39117" NonCompeteDistance="0" InteractByGossipOptions="1" MobState="Alive" X="2242.281" Y="230.375" Z="34.50985" />
    <RunTo X="2245.638" Y="232.9343" Z="41.81231" />
    <CustomBehavior File="WaitTimer" WaitTime="55000" />
  </While>
<!--
<Vendor Name="Shadow of Agamand" Entry="38981" Type="Repair" X="2246.242" Y="230.1794" Z="43.81334" />
-->
</If>
<TurnIn QuestName="The Grasp Weakens" QuestId="25006" TurnInName="Magistrate Sevren" TurnInId="1499" X="2315.887" Y="278.1732" Z="44.97721" />
<If Condition="!HasQuest(25007) &amp;&amp; !IsQuestCompleted(25007)">
  <PickUp QuestName="East... Always to the East" QuestId="25007" GiverName="Magistrate Sevren" GiverId="1499" X="2315.887" Y="278.1732" Z="44.97721" />
  <RunTo X="2302.5" Y="279.1147" Z="44.42836" />
  <CustomBehavior File="MyCTM" X="2278.517" Y="284.3423" Z="33.82134" />
</If>
<If Condition="!HasQuest(25056) &amp;&amp; !IsQuestCompleted(25056) &amp;&amp; Me.LevelFraction &gt;= 11.30">
  <CustomBehavior File="Message" Text="Moving to SILVERPINE FOREST, Please do not stop bot" LogColor="Aquamarine" />
  <PickUp QuestName="Warchief's Command: Silverpine Forest!" QuestId="26964" GiverName="Executor Zygand" GiverId="1515" X="2275.082" Y="297.6129" Z="33.64941" />
  <RunTo X="1421.067" Y="1019.964" Z="52.67456" />
  <CustomBehavior File="InteractWith" MobId="44825" MobState="Alive" X="1422.93" Y="1017.771" Z="52.56585" />
  <TurnIn QuestName="Warchief's Command: Silverpine Forest!" QuestId="26964" TurnInName="Grand Executor Mortuus" TurnInId="44615" X="1383" Y="1038.63" Z="54.31712" />
  <CustomBehavior File="LoadProfile" ProfileName="[H-Quest](11-20)SilverpineForest[Cava]" />
</If>
<If Condition="!HasQuest(25056) &amp;&amp; !IsQuestCompleted(25056)">
  <CustomBehavior File="ForceSetVendor" DoMail="True" DoSell="True" DoRepair="True" />
  <RunTo X="2272.68" Y="372.064" Z="35.7611" />
  <CustomBehavior File="Cava\TaxiRide" MobId="43124" DestName="The Bulwark" WaitTime="1000" />
  <RunTo X="1726.62" Y="-740.981" Z="59.9282" />
</If>
<PickUp QuestName="Grisly Grizzlies" QuestId="25056" GiverName="Apothecary Dithers" GiverId="11057" X="1751.823" Y="-729.9869" Z="60.06598" />
<TurnIn QuestName="East... Always to the East" QuestId="25007" TurnInName="High Executor Derrington" TurnInId="10837" X="1759.283" Y="-729.0208" Z="60.06607" />
<If Condition="!HasQuest(25009) &amp;&amp; !IsQuestCompleted(25009)">
  <PickUp QuestName="At War With The Scarlet Crusade" QuestId="25009" GiverName="High Executor Derrington" GiverId="10837" X="1759.283" Y="-729.0208" Z="60.06607" />
  <CustomBehavior File="Cava\SetHearthstone" MobId="46271" X="1668.34" Y="-720.995" Z="58.91577" /><!--ID =152-->
</If>
<Objective QuestName="Grisly Grizzlies" QuestId="25056" Type="CollectItem" ItemId="52270" CollectCount="5" />
<If Condition="HasQuest(25009) &amp;&amp; !IsQuestCompleted(25009)">
  <RunTo X="2120.868" Y="-567.9372" Z="71.1736" />
  <SetGrindArea>
    <GrindArea>
	<Factions>67</Factions>
    <Hotspots>
      <Hotspot X="2120.868" Y="-567.9372" Z="71.1736" />
      <Hotspot X="2157.752" Y="-583.1252" Z="79.3903" />
      <Hotspot X="2193.021" Y="-563.6572" Z="79.75726" />
      <Hotspot X="2186.709" Y="-523.0408" Z="79.46124" />
      <Hotspot X="2175.908" Y="-483.8297" Z="77.24616" />
      <Hotspot X="2155.008" Y="-449.9955" Z="71.05366" />
    </Hotspots>
  </GrindArea>
  </SetGrindArea>
  <GrindTo Condition="IsObjectiveComplete(1, 25009) || IsObjectiveComplete(2, 25009)" />
  <Objective QuestName="At War With The Scarlet Crusade" QuestId="25009" Type="KillMob" MobId="1537" KillCount="3" />
  <Objective QuestName="At War With The Scarlet Crusade" QuestId="25009" Type="KillMob" MobId="1538" KillCount="4" />
</If>
<TurnIn QuestName="At War With The Scarlet Crusade" QuestId="25009" TurnInName="High Executor Derrington" TurnInId="10837" X="1759.283" Y="-729.0208" Z="60.06607" />
<PickUp QuestName="A Deadly New Ally" QuestId="25010" GiverName="High Executor Derrington" GiverId="10837" X="1759.283" Y="-729.0208" Z="60.06607" />
<TurnIn QuestName="Grisly Grizzlies" QuestId="25056" TurnInName="Apothecary Dithers" TurnInId="11057" X="1751.823" Y="-729.9869" Z="60.06598" />
<PickUp QuestName="A Little Oomph" QuestId="25013" GiverName="Apothecary Dithers" GiverId="11057" X="1751.823" Y="-729.9869" Z="60.06598" />
<Objective QuestName="A Little Oomph" QuestId="25013" Type="CollectItem" ItemId="2872" CollectCount="4" />
<TurnIn QuestName="A Deadly New Ally" QuestId="25010" TurnInName="Lieutenant Sanders" TurnInId="13158" X="2533.339" Y="-920.6719" Z="60.98916" />
<PickUp QuestName="A Daughter's Embrace" QuestId="25046" GiverName="Lieutenant Sanders" GiverId="13158" X="2533.339" Y="-920.6719" Z="60.98916" />
<If Condition="HasQuest(25046) &amp;&amp; !IsQuestCompleted(25046)">
  <While Condition="!IsQuestCompleted(25046)">
    <If Condition="Me.HasAura(73306)" >
      <Runto X="2696.703" Y="-523.041" Z="101.5699" />
    </If>
    <If Condition="Me.HasAura(73306)" >
      <RunTo X="3075.463" Y="-559.8349" Z="126.7187" />
    </If>
    <If Condition="Me.HasAura(73306)" >
      <CustomBehavior File="WaitTimer" WaitTime="30000" />
    </If>
    <If Condition="!IsQuestCompleted(25046)">
      <CustomBehavior File="AbandonQuest" QuestId="25046" />
      <CustomBehavior File="WaitTimer" WaitTime="3000" />
      <PickUp QuestName="A Daughter's Embrace" QuestId="25046" GiverName="Lieutenant Sanders" GiverId="13158" X="2533.339" Y="-920.6719" Z="60.98916" />
      <CustomBehavior File="WaitTimer" WaitTime="2000" />
    </If>
  </While>
</If>
<If Condition="HasQuest(25013)">
  <CustomBehavior File="Cava\GoSavedInn" BindPointAreaId="152" />
</If>
<TurnIn QuestName="A Little Oomph" QuestId="25013" TurnInName="Apothecary Dithers" TurnInId="11057" X="1751.823" Y="-729.9869" Z="60.06598" />
<TurnIn QuestName="A Daughter's Embrace" QuestId="25046" TurnInName="High Executor Derrington" TurnInId="10837" X="1759.283" Y="-729.0208" Z="60.06602" />
<PickUp QuestName="To Bigger and Better Things" QuestId="25011" GiverName="High Executor Derrington" GiverId="10837" X="1759.283" Y="-729.0208" Z="60.06602" />
<TurnIn QuestName="To Bigger and Better Things" QuestId="25011" TurnInName="Timothy Cunningham" TurnInId="37915" X="1730.373" Y="-743.1945" Z="60.06481" />
<PickUp QuestName="Take to the Skies" QuestId="25012" GiverName="Timothy Cunningham" GiverId="37915" X="1730.373" Y="-743.1945" Z="60.06481" />
<If Condition="HasQuest(25012)">
  <CustomBehavior File="InteractWith" NonCompeteDistance="0" MobId="37915" MobState="Alive" InteractByGossipOptions="2" X="1730.373" Y="-743.1945" Z="60.06481" />
</If>
<TurnIn QuestName="Take to the Skies" QuestId="25012" TurnInName="Executor Zygand" TurnInId="1515" X="2275.082" Y="297.6129" Z="33.6494" />
<CustomBehavior File="Message" Text="Moving to SILVERPINE FOREST, Please do not stop bot" LogColor="Aquamarine" />
<PickUp QuestName="Warchief's Command: Silverpine Forest!" QuestId="26964" GiverName="Executor Zygand" GiverId="1515" X="2275.082" Y="297.6129" Z="33.64941" />
<RunTo X="1421.067" Y="1019.964" Z="52.67456" />
<CustomBehavior File="InteractWith" MobId="44825" MobState="Alive" X="1422.93" Y="1017.771" Z="52.56585" />
<TurnIn QuestName="Warchief's Command: Silverpine Forest!" QuestId="26964" TurnInName="Grand Executor Mortuus" TurnInId="44615" X="1383" Y="1038.63" Z="54.31712" />
<CustomBehavior File="LoadProfile" ProfileName="[H-Quest](11-20)SilverpineForest[Cava]" />
</QuestOrder>
</HBProfile>
