<HBProfile creator="Cava">
<Name>[N-Quest] (85-86) The Jade Forest [Cava] $Rev$</Name>

<MinLevel>5</MinLevel><MaxLevel>101</MaxLevel><MinDurability>0.2</MinDurability><MinFreeBagSlots>2</MinFreeBagSlots><TargetElites>False</TargetElites>
<MailGrey>False</MailGrey><MailWhite>False</MailWhite><MailGreen>True</MailGreen><MailBlue>True</MailBlue><MailPurple>True</MailPurple>
<SellGrey>True</SellGrey><SellWhite>True</SellWhite><SellGreen>False</SellGreen><SellBlue>False</SellBlue><SellPurple>False</SellPurple>
  
<AvoidMobs>
	<Mob Name="Jack Arrow" Id="63809" />
</AvoidMobs>
<Blacklist>
</Blacklist>
<Blackspots>
  <Blackspot X="2540.014" Y="-1008.177" Z="372.2065" Radius="20" />
</Blackspots>

<Mailboxes>
</Mailboxes>

<Vendors>
</Vendors>
<!-- ####################################### Quest Overrides ####################################################################### -->
<Quest Id="30069" Name="No Plan Survives Contact with the Enemy">
  <Objective Type="KillMob" MobId="66282" KillCount="6">
	  <Hotspots>
      <Hotspot X="-675.4255" Y="-1646.891" Z="18.91182" />
      <Hotspot X="-823.8742" Y="-1598.272" Z="0.7318842" />
      <Hotspot X="-733.913" Y="-1672.698" Z="16.43394" />
      <Hotspot X="-690.8334" Y="-1750.94" Z="6.031426" />
      <Hotspot X="-693.3765" Y="-1763.55" Z="1.93566" />
      <Hotspot X="-725.7912" Y="-1731.022" Z="27.75842" />
      <Hotspot X="-815.9385" Y="-1609.257" Z="0.9412893" />
      <Hotspot X="-663.3096" Y="-1694.13" Z="17.46247" />
      <Hotspot X="-716.6027" Y="-1677.946" Z="16.09574" />
		</Hotspots>
	</Objective>
  <Objective Type="KillMob" MobId="66290" KillCount="4">
	  <Hotspots>
      <Hotspot X="-675.4255" Y="-1646.891" Z="18.91182" />
      <Hotspot X="-823.8742" Y="-1598.272" Z="0.7318842" />
      <Hotspot X="-733.913" Y="-1672.698" Z="16.43394" />
      <Hotspot X="-690.8334" Y="-1750.94" Z="6.031426" />
		</Hotspots>
	</Objective>
</Quest>
<Quest Id="31737" Name="The Cost of War">
  <Objective Type="KillMob" MobId="66424" KillCount="5">
	  <Hotspots>
      <Hotspot X="-808.2877" Y="-1650.576" Z="3.782124" />
      <Hotspot X="-713.0797" Y="-1652.488" Z="16.08381" />
      <Hotspot X="-610.3044" Y="-1662.521" Z="12.58719" />
		</Hotspots>
	</Objective>
  <Objective Type="KillMob" MobId="66423" KillCount="15">
	  <Hotspots>
      <Hotspot X="-808.2877" Y="-1650.576" Z="3.782124" />
      <Hotspot X="-713.0797" Y="-1652.488" Z="16.08381" />
      <Hotspot X="-610.3044" Y="-1662.521" Z="12.58719" />
		</Hotspots>
	</Objective>
</Quest>
<Quest Id="31738" Name="Pillaging Peons">
  <Objective Type="KillMob" MobId="59979" KillCount="12">
	  <Hotspots>
      <Hotspot X="-443.1266" Y="-1563.94" Z="28.27024" />
      <Hotspot X="-485.9838" Y="-1506.734" Z="21.26701" />
      <Hotspot X="-410.5862" Y="-1445.66" Z="22.45845" />
      <Hotspot X="-406.4748" Y="-1515.459" Z="25.4865" />
      <Hotspot X="-311.0386" Y="-1569.802" Z="43.34619" />
		</Hotspots>
	</Objective>
</Quest>
<Quest Id="31740" Name="Koukou's Rampage">
  <Objective Type="KillMob" MobId="66213" KillCount="1">
	  <Hotspots>
      <Hotspot X="-533.3644" Y="-1296.528" Z="1.861906" />
		</Hotspots>
	</Objective>
</Quest>
<Quest Id="31744" Name="Unfair Trade">
  <Objective Type="KillMob" MobId="66367" KillCount="8">
	  <Hotspots>
      <Hotspot X="-165.766" Y="-1543.964" Z="72.84054" />
      <Hotspot X="-117.8475" Y="-1553.233" Z="72.84054" />
      <Hotspot X="-168.1282" Y="-1522.953" Z="72.84054" />
      <Hotspot X="-178.8496" Y="-1377.211" Z="72.58119" />
      <Hotspot X="-169.5622" Y="-1331.086" Z="72.58119" />
      <Hotspot X="-137.9102" Y="-1328.629" Z="72.58119" />
		</Hotspots>
	</Objective>
</Quest>
<Quest Id="31741" Name="Twinspire Keep">
  <Objective Type="KillMob" MobId="66267" KillCount="15">
	  <Hotspots>
      <Hotspot X="-165.766" Y="-1543.964" Z="72.84054" />
      <Hotspot X="-117.8475" Y="-1553.233" Z="72.84054" />
      <Hotspot X="-168.1282" Y="-1522.953" Z="72.84054" />
      <Hotspot X="-178.8496" Y="-1377.211" Z="72.58119" />
      <Hotspot X="-169.5622" Y="-1331.086" Z="72.58119" />
      <Hotspot X="-137.9102" Y="-1328.629" Z="72.58119" />
		</Hotspots>
	</Objective>
</Quest>
<Quest Id="31742" Name="Fractured Forces">
  <Objective Type="KillMob" MobId="66275" KillCount="1">
	  <Hotspots>
      <Hotspot X="-77.90344" Y="-1463.75" Z="128.1368" />
		</Hotspots>
	</Objective>
  <Objective Type="KillMob" MobId="66274" KillCount="1">
	  <Hotspots>
      <Hotspot X="-81.00426" Y="-1425.349" Z="128.1374" />
		</Hotspots>
	</Objective>
</Quest>
<Quest Id="30070" Name="The Fall of Ga'trul">
  <Objective Type="KillMob" MobId="66276" KillCount="1">
	  <Hotspots>
      <Hotspot X="42.56945" Y="-1434.332" Z="140.8309" />
		</Hotspots>
	</Objective>
</Quest>
<Quest Id="29556" Name="Hozen Aren't Your Friends, Hozen Are Your Enemies">
  <Objective Type="KillMob" MobId="66153" KillCount="14">
	  <Hotspots>
      <Hotspot X="-468.1469" Y="-2092.103" Z="19.78709" />
      <Hotspot X="-505.275" Y="-2051.688" Z="1.298151" />
      <Hotspot X="-474.2479" Y="-2047.356" Z="3.514092" />
      <Hotspot X="-505.9236" Y="-2000.464" Z="3.915246" />
      <Hotspot X="-559.1266" Y="-1991.095" Z="2.541532" />
		</Hotspots>
	</Objective>
</Quest>
<Quest Id="29560" Name="Ancient Power">
	<Objective Type="CollectItem" ItemId="74033" CollectCount="8">
		<CollectFrom>
		  <GameObject Name="Hozen Skull" Id="209595" />
		</CollectFrom>
		<Hotspots>
      <Hotspot X="-104.0896" Y="-2377.539" Z="33.28468" />
      <Hotspot X="-59.47893" Y="-2386.805" Z="35.15871" />
      <Hotspot X="-49.47919" Y="-2346.731" Z="33.41353" />
      <Hotspot X="-95.41581" Y="-2341.604" Z="33.16256" />
		</Hotspots>
	</Objective>
</Quest>
<Quest Id="29558" Name="The Path of War">
  <Objective Type="KillMob" MobId="55193" KillCount="12">
	  <Hotspots>
      <Hotspot X="-104.0896" Y="-2377.539" Z="33.28468" />
      <Hotspot X="-59.47893" Y="-2386.805" Z="35.15871" />
      <Hotspot X="-49.47919" Y="-2346.731" Z="33.41353" />
      <Hotspot X="-95.41581" Y="-2341.604" Z="33.16256" />
      <Hotspot X="-130.5539" Y="-2322.705" Z="31.36749" />
      <Hotspot X="-92.36929" Y="-2283.421" Z="30.05382" />
      <Hotspot X="-129.7766" Y="-2244.881" Z="34.92298" />
      <Hotspot X="-153.8823" Y="-2293.24" Z="31.70378" />
      <Hotspot X="-192.1511" Y="-2321.948" Z="35.47582" />
		</Hotspots>
	</Objective>
</Quest>
<Quest Id="29759" Name="Kung Din">
	<Objective Type="CollectItem" ItemId="79753" CollectCount="1">
		<CollectFrom>
      <Mob Id="59037" Name="Kung Din" />
		</CollectFrom>
		<Hotspots>
      <Hotspot X="-77.57258" Y="-2363.105" Z="27.99089" />
		</Hotspots>
	</Objective>
</Quest>
<Quest Id="29562" Name="Jailbreak">
  <Objective Type="KillMob" MobId="55195" KillCount="10">
	  <Hotspots>
      <Hotspot X="-178.4373" Y="-2433.18" Z="24.08242" />
      <Hotspot X="-145.8521" Y="-2464.193" Z="12.27715" />
		</Hotspots>
	</Objective>
</Quest>
<Quest Id="29885" Name="Road Rations">
	<Objective Type="CollectItem" ItemId="73368" CollectCount="6">
		<CollectFrom>
      <Mob Id="59084" Name="Pearly Tortoise" />
		</CollectFrom>
		<Hotspots>
      <Hotspot X="-304.9972" Y="-2565.298" Z="-1.941045" />
      <Hotspot X="-240.6853" Y="-2534.842" Z="-1.923201" />
      <Hotspot X="-216.3367" Y="-2579.618" Z="-1.934626" />
      <Hotspot X="-168.9752" Y="-2532.119" Z="-2.184522" />
		</Hotspots>
	</Objective>
</Quest>
<Quest Id="29887" Name="The Elder's Instruments">
	<Objective Type="CollectItem" ItemId="79807" CollectCount="1">
		<CollectFrom>
      <Mob Id="55110" Name="Slingtail Stickypaw" />
		</CollectFrom>
		<Hotspots>
      <Hotspot X="-426.8367" Y="-3139.069" Z="31.31693" />
      <Hotspot X="-439.5449" Y="-3203.679" Z="37.38247" />
      <Hotspot X="-428.9576" Y="-3246.795" Z="31.57241" />
      <Hotspot X="-435.1849" Y="-3281.656" Z="31.13518" />
      <Hotspot X="-402.3202" Y="-3287.6" Z="33.30472" />
      <Hotspot X="-391.5354" Y="-3225.823" Z="32.51514" />
      <Hotspot X="-371.6567" Y="-3168.389" Z="36.29922" />
		</Hotspots>
	</Objective>
	<Objective Type="CollectItem" ItemId="79808" CollectCount="1">
		<CollectFrom>
      <Mob Id="55110" Name="Slingtail Stickypaw" />
		</CollectFrom>
		<Hotspots>
      <Hotspot X="-426.8367" Y="-3139.069" Z="31.31693" />
      <Hotspot X="-439.5449" Y="-3203.679" Z="37.38247" />
      <Hotspot X="-428.9576" Y="-3246.795" Z="31.57241" />
      <Hotspot X="-435.1849" Y="-3281.656" Z="31.13518" />
      <Hotspot X="-402.3202" Y="-3287.6" Z="33.30472" />
      <Hotspot X="-391.5354" Y="-3225.823" Z="32.51514" />
      <Hotspot X="-371.6567" Y="-3168.389" Z="36.29922" />
		</Hotspots>
	</Objective>
	<Objective Type="CollectItem" ItemId="79809" CollectCount="1">
		<CollectFrom>
      <Mob Id="55110" Name="Slingtail Stickypaw" />
		</CollectFrom>
		<Hotspots>
      <Hotspot X="-426.8367" Y="-3139.069" Z="31.31693" />
      <Hotspot X="-439.5449" Y="-3203.679" Z="37.38247" />
      <Hotspot X="-428.9576" Y="-3246.795" Z="31.57241" />
      <Hotspot X="-435.1849" Y="-3281.656" Z="31.13518" />
      <Hotspot X="-402.3202" Y="-3287.6" Z="33.30472" />
      <Hotspot X="-391.5354" Y="-3225.823" Z="32.51514" />
      <Hotspot X="-371.6567" Y="-3168.389" Z="36.29922" />
		</Hotspots>
	</Objective>
	<Objective Type="CollectItem" ItemId="79810" CollectCount="1">
		<CollectFrom>
      <Mob Id="55110" Name="Slingtail Stickypaw" />
		</CollectFrom>
		<Hotspots>
      <Hotspot X="-426.8367" Y="-3139.069" Z="31.31693" />
      <Hotspot X="-439.5449" Y="-3203.679" Z="37.38247" />
      <Hotspot X="-428.9576" Y="-3246.795" Z="31.57241" />
      <Hotspot X="-435.1849" Y="-3281.656" Z="31.13518" />
      <Hotspot X="-402.3202" Y="-3287.6" Z="33.30472" />
      <Hotspot X="-391.5354" Y="-3225.823" Z="32.51514" />
      <Hotspot X="-371.6567" Y="-3168.389" Z="36.29922" />
		</Hotspots>
	</Objective>
</Quest>
<Quest Id="29906" Name="Carp Diem">
  <Objective Type="KillMob" MobId="54868" KillCount="1">
	  <Hotspots>
      <Hotspot X="-73.82058" Y="-2363.889" Z="27.99091" />
		</Hotspots>
	</Objective>
</Quest>
<Quest Id="29905" Name="Let Them Burn">
  <Objective Type="KillMob" MobId="55461" KillCount="15">
	  <Hotspots>
      <Hotspot X="-121.5947" Y="-2419.226" Z="26.77358" />
      <Hotspot X="-171.6617" Y="-2393.641" Z="31.12641" />
      <Hotspot X="-155.9776" Y="-2357.656" Z="32.64159" />
      <Hotspot X="-181.8563" Y="-2337.473" Z="34.46997" />
		</Hotspots>
	</Objective>
</Quest>
<Quest Id="29891" Name="Potency">
  <Objective Type="KillMob" MobId="56304" KillCount="8">
	  <Hotspots>
      <Hotspot X="-654.2847" Y="-2435.005" Z="26.4146" />
      <Hotspot X="-654.2847" Y="-2435.005" Z="26.4146" />
      <Hotspot X="-689.2635" Y="-2532.481" Z="26.06712" />
      <Hotspot X="-675.3683" Y="-2611.612" Z="19.3764" />
      <Hotspot X="-619.6975" Y="-2683.45" Z="9.990462" />
		</Hotspots>
	</Objective>
	<Objective Type="CollectItem" ItemId="76129" CollectCount="1">
		<CollectFrom>
      <Mob Id="56310" Name="Mist Horror" />
		</CollectFrom>
		<Hotspots>
      <Hotspot X="-654.2847" Y="-2435.005" Z="26.4146" />
      <Hotspot X="-654.2847" Y="-2435.005" Z="26.4146" />
      <Hotspot X="-689.2635" Y="-2532.481" Z="26.06712" />
      <Hotspot X="-675.3683" Y="-2611.612" Z="19.3764" />
      <Hotspot X="-619.6975" Y="-2683.45" Z="9.990462" />
		</Hotspots>
	</Objective>
</Quest>
<Quest Id="29892" Name="Body">
	<Objective Type="CollectItem" ItemId="76107" CollectCount="5">
		<CollectFrom>
      <Mob Id="54558" Name="Bog Crocolisk" />
		</CollectFrom>
		<Hotspots>
      <Hotspot X="-533.4677" Y="-2697.265" Z="0.890718" />
      <Hotspot X="-485.3233" Y="-2758.262" Z="3.865064" />
      <Hotspot X="-516.2355" Y="-2849.414" Z="2.824336" />
      <Hotspot X="-506.7089" Y="-2904.206" Z="-1.313707" />
		</Hotspots>
	</Objective>
</Quest>
<Quest Id="29900" Name="An Ancient Legend">
  <Objective Type="KillMob" MobId="56441" KillCount="1">
	  <Hotspots>
      <Hotspot X="-83.3475" Y="-3210.947" Z="81.38386" />
		</Hotspots>
	</Objective>
</Quest>
<Quest Id="29899" Name="Rest in Peace">
  <Objective Type="KillMob" MobId="56444" KillCount="6">
	  <Hotspots>
      <Hotspot X="-148.7483" Y="-3242.795" Z="65.39949" />
      <Hotspot X="-141.8104" Y="-3289.149" Z="75.25442" />
      <Hotspot X="-208.1416" Y="-3229.102" Z="57.16092" />
      <Hotspot X="-171.6595" Y="-3196.155" Z="51.24582" />
      <Hotspot X="-165.5485" Y="-3156.458" Z="47.26645" />
      <Hotspot X="-139.3324" Y="-3139.93" Z="42.14346" />
      <Hotspot X="-168.4885" Y="-3089.264" Z="35.3804" />
		</Hotspots>
	</Objective>
</Quest>
<Quest Id="31767" Name="Finish Them!">
  <Objective Type="KillMob" MobId="66285" KillCount="15">
	  <Hotspots>
      <Hotspot X="3349.447" Y="-808.7408" Z="245.9961" />
      <Hotspot X="3358.858" Y="-848.1661" Z="245.9961" />
      <Hotspot X="3333.254" Y="-879.9469" Z="245.9961" />
      <Hotspot X="3301.869" Y="-905.6469" Z="249.4683" />
      <Hotspot X="3265.738" Y="-922.0533" Z="257.4446" />
      <Hotspot X="3248.813" Y="-958.807" Z="257.4779" />
      <Hotspot X="3256.057" Y="-998.2667" Z="257.4444" />
      <Hotspot X="3295.863" Y="-989.5014" Z="257.4444" />
      <Hotspot X="3219.405" Y="-946.2953" Z="268.2709" />
		</Hotspots>
	</Objective>
</Quest>
<Quest Id="31771" Name="Face to Face With Consequence">
  <Objective Type="KillMob" MobId="66426" KillCount="7">
	  <Hotspots>
      <Hotspot X="3160.01" Y="-893.2589" Z="324.6956" />
      <Hotspot X="3158.703" Y="-943.8558" Z="324.6956" />
      <Hotspot X="3173.96" Y="-988.2761" Z="307.3627" />
      <Hotspot X="3195.133" Y="-944.6015" Z="292.5168" />
      <Hotspot X="3160.316" Y="-911.4626" Z="278.6332" />
      <Hotspot X="3193.974" Y="-875.7347" Z="268.2515" />
      <Hotspot X="3215.825" Y="-922.2249" Z="268.2618" />
      <Hotspot X="3259.934" Y="-945.2288" Z="257.4445" />
      <Hotspot X="3298.272" Y="-913.1346" Z="253.8909" />
      <Hotspot X="3312.63" Y="-865.0236" Z="245.9958" />
      <Hotspot X="3332.482" Y="-817.6295" Z="245.9964" />
		</Hotspots>
	</Objective>
  <Objective Type="KillMob" MobId="66425" KillCount="20">
	  <Hotspots>
      <Hotspot X="3160.01" Y="-893.2589" Z="324.6956" />
      <Hotspot X="3158.703" Y="-943.8558" Z="324.6956" />
      <Hotspot X="3173.96" Y="-988.2761" Z="307.3627" />
      <Hotspot X="3195.133" Y="-944.6015" Z="292.5168" />
      <Hotspot X="3160.316" Y="-911.4626" Z="278.6332" />
      <Hotspot X="3193.974" Y="-875.7347" Z="268.2515" />
      <Hotspot X="3215.825" Y="-922.2249" Z="268.2618" />
      <Hotspot X="3259.934" Y="-945.2288" Z="257.4445" />
      <Hotspot X="3298.272" Y="-913.1346" Z="253.8909" />
      <Hotspot X="3312.63" Y="-865.0236" Z="245.9958" />
      <Hotspot X="3332.482" Y="-817.6295" Z="245.9964" />
		</Hotspots>
	</Objective>
</Quest>
<Quest Id="31773" Name="Prowler Problems">
  <Objective Type="KillMob" MobId="66668" KillCount="10">
	  <Hotspots>
      <Hotspot X="3234.558" Y="-538.9208" Z="236.55" />
      <Hotspot X="3205.774" Y="-581.3829" Z="232.3105" />
      <Hotspot X="3163.154" Y="-610.41" Z="232.6489" />
      <Hotspot X="3114.146" Y="-623.8397" Z="231.3827" />
      <Hotspot X="3079.755" Y="-660.6155" Z="230.6759" />
      <Hotspot X="3041.621" Y="-695.8842" Z="227.7125" />
      <Hotspot X="3035.002" Y="-745.4833" Z="226.8967" />
      <Hotspot X="3076.919" Y="-773.2461" Z="227.8914" />
      <Hotspot X="3127.98" Y="-771.3361" Z="227.9437" />
      <Hotspot X="3162.619" Y="-733.5692" Z="229.2578" />
      <Hotspot X="3206.271" Y="-707.342" Z="234.8458" />
		</Hotspots>
	</Objective>
</Quest>
<Quest Id="29765" Name="Cryin' My Eyes Out">
	<Objective Type="CollectItem" ItemId="74160" CollectCount="1">
		<Hotspots>
      <Hotspot X="2840.726" Y="-718.9996" Z="257.6598" />
      <Hotspot X="2868.075" Y="-677.3618" Z="250.7855" />
      <Hotspot X="2856.235" Y="-627.9182" Z="247.5759" />
      <Hotspot X="2838.959" Y="-580.1931" Z="245.6789" />
      <Hotspot X="2790.65" Y="-567.0085" Z="254.3506" />
      <Hotspot X="2752.227" Y="-597.4379" Z="269.0921" />
      <Hotspot X="2782.843" Y="-637.8149" Z="264.5583" />
      <Hotspot X="2820.324" Y="-670.9388" Z="260.6511" />
		</Hotspots>
	</Objective>
	<Objective Type="CollectItem" ItemId="74161" CollectCount="1">
		<Hotspots>
      <Hotspot X="2840.726" Y="-718.9996" Z="257.6598" />
      <Hotspot X="2868.075" Y="-677.3618" Z="250.7855" />
      <Hotspot X="2856.235" Y="-627.9182" Z="247.5759" />
      <Hotspot X="2838.959" Y="-580.1931" Z="245.6789" />
      <Hotspot X="2790.65" Y="-567.0085" Z="254.3506" />
      <Hotspot X="2752.227" Y="-597.4379" Z="269.0921" />
      <Hotspot X="2782.843" Y="-637.8149" Z="264.5583" />
      <Hotspot X="2820.324" Y="-670.9388" Z="260.6511" />
    </Hotspots>
	</Objective>
	<Objective Type="CollectItem" ItemId="74162" CollectCount="1">
		<Hotspots>
      <Hotspot X="2840.726" Y="-718.9996" Z="257.6598" />
      <Hotspot X="2868.075" Y="-677.3618" Z="250.7855" />
      <Hotspot X="2856.235" Y="-627.9182" Z="247.5759" />
      <Hotspot X="2838.959" Y="-580.1931" Z="245.6789" />
      <Hotspot X="2790.65" Y="-567.0085" Z="254.3506" />
      <Hotspot X="2752.227" Y="-597.4379" Z="269.0921" />
      <Hotspot X="2782.843" Y="-637.8149" Z="264.5583" />
      <Hotspot X="2820.324" Y="-670.9388" Z="260.6511" />
    </Hotspots>
  </Objective>
	<Objective Type="CollectItem" ItemId="74163" CollectCount="1">
		<Hotspots>
      <Hotspot X="2840.726" Y="-718.9996" Z="257.6598" />
      <Hotspot X="2868.075" Y="-677.3618" Z="250.7855" />
      <Hotspot X="2856.235" Y="-627.9182" Z="247.5759" />
      <Hotspot X="2838.959" Y="-580.1931" Z="245.6789" />
      <Hotspot X="2790.65" Y="-567.0085" Z="254.3506" />
      <Hotspot X="2752.227" Y="-597.4379" Z="269.0921" />
      <Hotspot X="2782.843" Y="-637.8149" Z="264.5583" />
      <Hotspot X="2820.324" Y="-670.9388" Z="260.6511" />
		</Hotspots>
	</Objective>
</Quest>
<Quest Id="29804" Name="Seein' Red">
  <Objective Type="KillMob" MobId="55509" KillCount="1">
	  <Hotspots>
      <Hotspot X="2618.931" Y="-777.6875" Z="316.7683" />
		</Hotspots>
	</Objective>
</Quest>
<Quest Id="31776" Name="Strongarm Tactics">
  <Objective Type="KillMob" MobId="65880" KillCount="1">
	  <Hotspots>
      <Hotspot X="2576.408" Y="-619.3438" Z="341.6442" />
		</Hotspots>
	</Objective>
  <Objective Type="KillMob" MobId="65881" KillCount="1">
	  <Hotspots>
      <Hotspot X="2585.274" Y="-488.1129" Z="348.4313" />
		</Hotspots>
	</Objective>
</Quest>
<Quest Id="31775" Name="Assault on the Airstrip">
  <Objective Type="KillMob" MobId="65841" KillCount="15">
	  <Hotspots>
      <Hotspot X="2578.812" Y="-511.2899" Z="342.5257" />
      <Hotspot X="2533.286" Y="-487.886" Z="341.6528" />
      <Hotspot X="2513.981" Y="-534.5096" Z="341.523" />
      <Hotspot X="2526.166" Y="-583.366" Z="350.2509" />
      <Hotspot X="2525.478" Y="-633.386" Z="355.5562" />
      <Hotspot X="2573.736" Y="-637.157" Z="341.2538" />
		</Hotspots>
	</Objective>
</Quest>
<Quest Id="31779" Name="The Darkness Within">
  <Objective Type="KillMob" MobId="66052" KillCount="1">
	  <Hotspots>
      <Hotspot X="2552.141" Y="-346.4496" Z="343.6661" />
		</Hotspots>
	</Objective>
</Quest>
<Quest Id="31112" Name="They're So Thorny!">
  <Objective Type="CollectItem" ItemId="74623" CollectCount="5">
	  <CollectFrom>
		  <Mob Name="Water Sprite" Entry="62930" />
 		</CollectFrom>
		<Hotspots>
      <Hotspot X="2357.857" Y="-335.7583" Z="315.1318" />
      <Hotspot X="2370.215" Y="-286.1725" Z="320.5547" />
      <Hotspot X="2415.894" Y="-264.8028" Z="320.2227" />
      <Hotspot X="2436.739" Y="-311.4914" Z="318.8805" />
      <Hotspot X="2449.484" Y="-360.8675" Z="315.5843" />
      <Hotspot X="2433.683" Y="-407.0838" Z="326.43" />
      <Hotspot X="2255.473" Y="-384.2362" Z="317.0437" />
      <Hotspot X="2293.905" Y="-349.2611" Z="316.921" />
		</Hotspots>
	</Objective>
</Quest>
<Quest Id="29822" Name="Lay of the Land">
  <Objective Type="KillMob" MobId="55622" KillCount="1">
	  <Hotspots>
      <Hotspot X="2241.417" Y="-489.9809" Z="368.54" />
		</Hotspots>
	</Objective>
</Quest>
<Quest Id="29879" Name="Swallowed Whole">
  <Objective Type="KillMob" MobId="56183" KillCount="5">
	  <Hotspots>
      <Hotspot X="2085.982" Y="-296.3678" Z="387.2096" />
      <Hotspot X="2051.85" Y="-259.4094" Z="389.0306" />
      <Hotspot X="2012.359" Y="-228.1152" Z="387.3336" />
      <Hotspot X="1968.701" Y="-252.503" Z="388.0918" />
		</Hotspots>
	</Objective>
</Quest>
<Quest Id="29924" Name="Kill Kher Shan">
  <Objective Type="KillMob" MobId="56329" KillCount="1">
	  <Hotspots>
      <Hotspot X="1713.418" Y="-876.9288" Z="304.9293" />
		</Hotspots>
	</Objective>
</Quest>
<Quest Id="31241" Name="Wicked Wikkets">
  <Objective Type="CollectItem" ItemId="85784" CollectCount="6">
	  <CollectFrom>
		  <Mob Name="Battleworn Paratrooper" Entry="63782" />
 		</CollectFrom>
		<Hotspots>
      <Hotspot X="1741.087" Y="-801.5925" Z="329.8571" />
      <Hotspot X="1764.814" Y="-757.1686" Z="320.1576" />
      <Hotspot X="1789.107" Y="-712.9063" Z="327.0899" />
      <Hotspot X="1809.218" Y="-667.381" Z="331.9163" />
      <Hotspot X="1788.357" Y="-621.853" Z="336.6461" />
      <Hotspot X="1738.58" Y="-618.0372" Z="333.7931" />
      <Hotspot X="1706.837" Y="-656.7444" Z="327.9829" />
      <Hotspot X="1697.821" Y="-705.8167" Z="320.6441" />
		</Hotspots>
	</Objective>
</Quest>
<Quest Id="29933" Name="The Bees' Knees">
  <Objective Type="CollectItem" ItemId="76173" CollectCount="30">
	  <CollectFrom>
		  <Mob Name="Tigerfly" Entry="56283" />
 		</CollectFrom>
		<Hotspots>
      <Hotspot X="1549.277" Y="-867.6382" Z="282.3046" />
      <Hotspot X="1543.919" Y="-818.0436" Z="288.5841" />
      <Hotspot X="1547.373" Y="-768.3799" Z="294.1795" />
      <Hotspot X="1558.449" Y="-719.1409" Z="304.3807" />
      <Hotspot X="1579.03" Y="-673.2261" Z="313.5708" />
      <Hotspot X="1594.517" Y="-625.0454" Z="315.5352" />
      <Hotspot X="1610.474" Y="-576.0005" Z="317.4363" />
		</Hotspots>
	</Objective>
</Quest>
<Quest Id="31239" Name="What's in a Name Name?">
  <Objective Type="KillMob" MobId="56289" KillCount="7">
	  <Hotspots>
      <Hotspot X="1555.794" Y="-516.0032" Z="317.797" />
      <Hotspot X="1514.631" Y="-544.6747" Z="313.5116" />
      <Hotspot X="1558.687" Y="-567.3074" Z="305.6876" />
      <Hotspot X="1578.639" Y="-613.3793" Z="308.2901" />
      <Hotspot X="1553.909" Y="-657.031" Z="299.1068" />
      <Hotspot X="1539.874" Y="-705.3661" Z="294.5105" />
      <Hotspot X="1533.228" Y="-755.7865" Z="292.9837" />
      <Hotspot X="1480.196" Y="-791.1565" Z="290.105" />
      <Hotspot X="1458.725" Y="-744.1114" Z="293.1094" />
      <Hotspot X="1451.121" Y="-695.676" Z="307.177" />
		</Hotspots>
	</Objective>
</Quest>
<Quest Id="29937" Name="Furious Fowl">
  <Objective Type="CollectItem" ItemId="76225" CollectCount="6">
	  <CollectFrom>
		  <Mob Name="Hungry Bloodtalon" Entry="56396" />
 		</CollectFrom>
		<Hotspots>
      <Hotspot X="1379.632" Y="-592.08" Z="339.0418" />
      <Hotspot X="1335.415" Y="-617.6235" Z="336.3083" />
      <Hotspot X="1351.182" Y="-665.5242" Z="330.7318" />
      <Hotspot X="1401.497" Y="-658.7482" Z="326.6206" />
      <Hotspot X="1298.433" Y="-641.1896" Z="330.8586" />
      <Hotspot X="1248.221" Y="-641.6508" Z="328.3256" />
      <Hotspot X="1246.433" Y="-591.0252" Z="329.0858" />
		</Hotspots>
	</Objective>
</Quest>
<Quest Id="29942" Name="Silly Wikket, Slickies are for Hozen">
  <Objective Type="CollectItem" ItemId="76420" CollectCount="4">
	  <CollectFrom>
		  <Mob Name="Muck Snapper" Entry="56447" />
 		</CollectFrom>
		<Hotspots>
      <Hotspot X="1137.798" Y="-447.0649" Z="272.075" />
      <Hotspot X="1090.161" Y="-431.4229" Z="259.6334" />
		</Hotspots>
	</Objective>
</Quest>
<Quest Id="29968" Name="Green-ish Energy">
	<Objective Type="CollectItem" ItemId="76333" CollectCount="7">
		<CollectFrom>
		  <GameObject Name="Green Branch" Id="209903" />
		</CollectFrom>
		<Hotspots>
      <Hotspot X="1222.021" Y="-707.8384" Z="324.17" />
      <Hotspot X="1181.194" Y="-703.188" Z="323.0096" />
      <Hotspot X="1146.333" Y="-723.3966" Z="325.5258" />
      <Hotspot X="1152.754" Y="-763.1414" Z="325.1519" />
      <Hotspot X="1186.656" Y="-781.5182" Z="310.4771" />
      <Hotspot X="1225.506" Y="-789.9969" Z="303.2288" />
      <Hotspot X="1251.76" Y="-761.8508" Z="317.5788" />
      <Hotspot X="1290.283" Y="-751.6398" Z="323.2009" />
      <Hotspot X="1296.935" Y="-710.5466" Z="326.9074" />
      <Hotspot X="1278.841" Y="-674.0369" Z="327.4047" />
      <Hotspot X="1251.924" Y="-643.0135" Z="327.5321" />
		</Hotspots>
	</Objective>
</Quest>
<Quest Id="29943" Name="Guerrillas in our Midst">
  <Objective Type="KillMob" MobId="56303" KillCount="8">
	  <Hotspots>
      <Hotspot X="1222.021" Y="-707.8384" Z="324.17" />
      <Hotspot X="1181.194" Y="-703.188" Z="323.0096" />
      <Hotspot X="1146.333" Y="-723.3966" Z="325.5258" />
      <Hotspot X="1152.754" Y="-763.1414" Z="325.1519" />
      <Hotspot X="1186.656" Y="-781.5182" Z="310.4771" />
      <Hotspot X="1225.506" Y="-789.9969" Z="303.2288" />
      <Hotspot X="1251.76" Y="-761.8508" Z="317.5788" />
      <Hotspot X="1290.283" Y="-751.6398" Z="323.2009" />
      <Hotspot X="1296.935" Y="-710.5466" Z="326.9074" />
      <Hotspot X="1278.841" Y="-674.0369" Z="327.4047" />
      <Hotspot X="1251.924" Y="-643.0135" Z="327.5321" />
		</Hotspots>
	</Objective>
</Quest>
<Quest Id="29866" Name="The Threads that Stick">
	<Objective Type="CollectItem" ItemId="75023" CollectCount="7">
		<CollectFrom>
		  <GameObject Name="Silk Patch" Id="209951" />
		  <GameObject Name="Silk Patch" Id="209833" />
		  <GameObject Name="Silk Patch" Id="209826" />
		</CollectFrom>
		<Hotspots>
      <Hotspot X="1336.648" Y="-1665.314" Z="220.0438" />
      <Hotspot X="1361.466" Y="-1599.66" Z="250.7068" />
      <Hotspot X="1384.462" Y="-1550.279" Z="269.9716" />
      <Hotspot X="1400.778" Y="-1500.676" Z="282.0865" />
      <Hotspot X="1335.788" Y="-1475.473" Z="264.9185" />
      <Hotspot X="1261.8" Y="-1466.167" Z="252.7963" />
      <Hotspot X="1243.588" Y="-1516.693" Z="244.8603" />
      <Hotspot X="1274.096" Y="-1574.059" Z="236.3909" />
		</Hotspots>
	</Objective>
</Quest>
<Quest Id="29865" Name="The Silkwood Road">
  <Objective Type="KillMob" MobId="56070" KillCount="8">
	  <Hotspots>
      <Hotspot X="1336.648" Y="-1665.314" Z="220.0438" />
      <Hotspot X="1361.466" Y="-1599.66" Z="250.7068" />
      <Hotspot X="1384.462" Y="-1550.279" Z="269.9716" />
      <Hotspot X="1400.778" Y="-1500.676" Z="282.0865" />
      <Hotspot X="1335.788" Y="-1475.473" Z="264.9185" />
      <Hotspot X="1261.8" Y="-1466.167" Z="252.7963" />
      <Hotspot X="1243.588" Y="-1516.693" Z="244.8603" />
      <Hotspot X="1274.096" Y="-1574.059" Z="236.3909" />
		</Hotspots>
	</Objective>
</Quest>
<Quest Id="29717" Name="Down Kitty!">
  <Objective Type="KillMob" MobId="55236" KillCount="8">
	  <Hotspots>
      <Hotspot X="1592.712" Y="-1273.666" Z="243.8448" />
      <Hotspot X="1636.948" Y="-1329.134" Z="243.2588" />
      <Hotspot X="1712.366" Y="-1313.301" Z="244.9406" />
      <Hotspot X="1680.894" Y="-1262.183" Z="249.6182" />
      <Hotspot X="1620.433" Y="-1235.604" Z="244.9158" />
      <Hotspot X="1564.323" Y="-1270.363" Z="242.4313" />
		</Hotspots>
	</Objective>
</Quest>
<Quest Id="29881" Name="The Perfect Color">
	<Objective Type="CollectItem" ItemId="75219" CollectCount="8">
		<CollectFrom>
		  <GameObject Name="Freshly Fallen Petals" Id="209836" />
		</CollectFrom>
		<Hotspots>
      <Hotspot X="1647.195" Y="-2324.054" Z="159.0822" />
      <Hotspot X="1560.852" Y="-2186.425" Z="159.382" />
      <Hotspot X="1590.736" Y="-2279.066" Z="153.6632" />
      <Hotspot X="1685.029" Y="-2404.965" Z="155.7498" />
      <Hotspot X="1683.315" Y="-2475.101" Z="152.5546" />
		</Hotspots>
	</Objective>
</Quest>
<Quest Id="29882" Name="Quill of Stingers">
	<Objective Type="CollectItem" ItemId="75221" CollectCount="6">
		<CollectFrom>
      <Mob Id="56201" Name="Orchard Wasp" />
		</CollectFrom>
		<Hotspots>
      <Hotspot X="1647.195" Y="-2324.054" Z="159.0822" />
      <Hotspot X="1560.852" Y="-2186.425" Z="159.382" />
      <Hotspot X="1590.736" Y="-2279.066" Z="153.6632" />
      <Hotspot X="1685.029" Y="-2404.965" Z="155.7498" />
      <Hotspot X="1683.315" Y="-2475.101" Z="152.5546" />
		</Hotspots>
	</Objective>
</Quest>
<Quest Id="29928" Name="I Have No Jade And I Must Scream">
	<Objective Type="CollectItem" ItemId="76209" CollectCount="15">
		<CollectFrom>
		  <Mob Id="56349" Name="Puckish Sprite" />
		  <GameObject Name="Chunk of Jade" Id="209863" />
		</CollectFrom>
		<Hotspots>
      <Hotspot X="2231.843" Y="-1960.569" Z="223.3759" />
      <Hotspot X="2175.657" Y="-1902.021" Z="219.0452" />
      <Hotspot X="2125.428" Y="-1939.749" Z="217.9374" />
      <Hotspot X="2165.321" Y="-1983.562" Z="223.81" />
		</Hotspots>
	</Objective>
</Quest>
<Quest Id="29926" Name="Calamity Jade">
  <Objective Type="KillMob" MobId="56404" KillCount="6">
	  <Hotspots>
      <Hotspot X="2334.537" Y="-1764.31" Z="185.0424" />
      <Hotspot X="2271.888" Y="-1698.238" Z="186.2353" />
      <Hotspot X="2219.628" Y="-1655.71" Z="185.9755" />
      <Hotspot X="2246.192" Y="-1612.085" Z="186.1667" />
      <Hotspot X="2297.208" Y="-1622.19" Z="180.3879" />
      <Hotspot X="2347.103" Y="-1644.108" Z="184.6198" />
		</Hotspots>
	</Objective>
  <Objective Type="KillMob" MobId="56401" KillCount="12">
	  <Hotspots>
      <Hotspot X="2334.537" Y="-1764.31" Z="185.0424" />
      <Hotspot X="2271.888" Y="-1698.238" Z="186.2353" />
      <Hotspot X="2219.628" Y="-1655.71" Z="185.9755" />
      <Hotspot X="2246.192" Y="-1612.085" Z="186.1667" />
      <Hotspot X="2297.208" Y="-1622.19" Z="180.3879" />
      <Hotspot X="2347.103" Y="-1644.108" Z="184.6198" />
		</Hotspots>
	</Objective>
</Quest>
<Quest Id="29745" Name="The Sprites' Plight">
  <Objective Type="KillMob" MobId="55288" KillCount="10">
	  <Hotspots>
      <Hotspot X="2739.438" Y="-2013.769" Z="197.9072" />
      <Hotspot X="2660.171" Y="-1979.355" Z="212.721" />
      <Hotspot X="2603.401" Y="-1958.222" Z="219.1385" />
      <Hotspot X="2526.277" Y="-1956.961" Z="219.1596" />
		</Hotspots>
	</Objective>
</Quest>
<Quest Id="29747" Name="Break the Cycle">
  <Objective Type="KillMob" MobId="55279" KillCount="8">
	  <Hotspots>
      <Hotspot X="2710.842" Y="-1933.559" Z="214.7956" />
      <Hotspot X="2768.981" Y="-1929.216" Z="214.2207" />
      <Hotspot X="2813.944" Y="-1938.779" Z="213.3031" />
      <Hotspot X="2872.224" Y="-1931.702" Z="212.6731" />
      <Hotspot X="2888.313" Y="-1841.142" Z="233.939" />
      <Hotspot X="2885.9" Y="-1795.376" Z="233.143" />
		</Hotspots>
	</Objective>
</Quest>
<Quest Id="29749" Name="An Urgent Plea">
	<Objective Type="CollectItem" ItemId="74258" CollectCount="1">
		<CollectFrom>
		  <GameObject Name="Staff of Pei-Zhi" Id="209629" />
		</CollectFrom>
		<Hotspots>
			<Hotspot X="2955.592" Y="-1636.98" Z="252.8331" />
		</Hotspots>
	</Objective>
</Quest>
<Quest Id="29751" Name="Ritual Artifacts">
	<Objective Type="CollectItem" ItemId="74762" CollectCount="1">
		<CollectFrom>
		  <GameObject Name="Jade Cong" Id="209699" />
		</CollectFrom>
		<Hotspots>
      <Hotspot X="2920.738" Y="-1527.284" Z="255.8835" />
		</Hotspots>
	</Objective>
	<Objective Type="CollectItem" ItemId="74761" CollectCount="1">
		<CollectFrom>
		  <GameObject Name="Pungent Ritual Candle" Id="209701" />
		</CollectFrom>
		<Hotspots>
      <Hotspot X="2855.894" Y="-1501.322" Z="273.0155" />
		</Hotspots>
	</Objective>
	<Objective Type="CollectItem" ItemId="74760" CollectCount="1">
		<CollectFrom>
		  <GameObject Name="Chipped Ritual Bowl" Id="209700" />
		</CollectFrom>
		<Hotspots>
      <Hotspot X="2985.999" Y="-1454.534" Z="244.9068" />
		</Hotspots>
	</Objective>
</Quest>
<Quest Id="29750" Name="Vessels of the Spirit">
	<Objective Type="CollectItem" ItemId="74763" CollectCount="8">
		<CollectFrom>
      <Mob Id="55291" Name="Shan'ze Spiritclaw" />
		</CollectFrom>
		<Hotspots>
		  <Hotspot X="2963.413" Y="-1452.859" Z="244.1403" />
    <Hotspot X="2972.904" Y="-1399.264" Z="244.1403" />
    <Hotspot X="2969.448" Y="-1361.619" Z="246.2379" />
    <Hotspot X="2909.332" Y="-1514.186" Z="255.8839" />
    <Hotspot X="2856.351" Y="-1475.471" Z="275.5011" />
		</Hotspots>
	</Objective>
</Quest>
<Quest Id="29756" Name="A Humble Offering">
	<Objective Type="CollectItem" ItemId="75214" CollectCount="10">
		<CollectFrom>
		  <GameObject Name="Tidemist Cap" Id="209825" />
		</CollectFrom>
		<Hotspots>
      <Hotspot X="3117.439" Y="-1382.975" Z="207.7039" />
      <Hotspot X="3086.218" Y="-1330.28" Z="207.1931" />
      <Hotspot X="3075.495" Y="-1264.66" Z="198.8451" />
      <Hotspot X="3166.342" Y="-1242.73" Z="201.1071" />
      <Hotspot X="3167.155" Y="-1299.572" Z="203.5085" />
      <Hotspot X="3162.051" Y="-1390.136" Z="210.0857" />
		</Hotspots>
	</Objective>
</Quest>
<Quest Id="29619" Name="A Courteous Guest">
	<Objective Type="CollectItem" ItemId="72589" CollectCount="8">
		<CollectFrom>
		  <GameObject Name="Ripe Orange" Id="209436" />
		  <Mob Id="54930" Name="Greenwood Thief" />
		</CollectFrom>
		<Hotspots>
      <Hotspot X="2393.848" Y="-1743.052" Z="373.6489" />
      <Hotspot X="2333.073" Y="-1707.295" Z="325.4108" />
		</Hotspots>
	</Objective>
</Quest>
<Quest Id="29627" Name="A Proper Weapon">
	<Objective Type="CollectItem" ItemId="72926" CollectCount="6">
		<CollectFrom>
		  <GameObject Name="Rattan Switch" Id="209461" />
		  <GameObject Name="Rattan Switch" Id="209462" />
		  <GameObject Name="Rattan Switch" Id="209463" />
		  <GameObject Name="Rattan Switch" Id="209464" />
		</CollectFrom>
		<Hotspots>
      <Hotspot X="2502.554" Y="-1451.231" Z="388.1611" />
      <Hotspot X="2440.42" Y="-1504.428" Z="392.4036" />
      <Hotspot X="2482.74" Y="-1505.414" Z="389.1071" />
      <Hotspot X="2545.373" Y="-1500.24" Z="396.7703" />
      <Hotspot X="2563.949" Y="-1437.936" Z="406.9931" />
		</Hotspots>
	</Objective>
</Quest>
<Quest Id="29631" Name="Burning Bright">
  <Objective Type="KillMob" MobId="54988" KillCount="6">
		<Hotspots>
      <Hotspot X="2579.208" Y="-1051.186" Z="360.9216" />
      <Hotspot X="2574.646" Y="-989.2601" Z="361.86" />
      <Hotspot X="2558.058" Y="-944.2395" Z="366.3159" />
      <Hotspot X="2622.862" Y="-989.6108" Z="353.845" />
      <Hotspot X="2664.051" Y="-958.7451" Z="345.6852" />
      <Hotspot X="2706.771" Y="-925.1069" Z="330.3941" />
      <Hotspot X="2691.254" Y="-962.2443" Z="341.1428" />
      <Hotspot X="2660.209" Y="-1005.319" Z="351.6455" />
      <Hotspot X="2668.161" Y="-1064.728" Z="348.4767" />
		</Hotspots>
	</Objective>
</Quest>
<Quest Id="29630" Name="And a Heavy Fist">
  <Objective Type="KillMob" MobId="54987" KillCount="10">
	  <Hotspots>
      <Hotspot X="2790.593" Y="-1220.896" Z="341.5711" />
      <Hotspot X="2686.374" Y="-1155.66" Z="354.6712" />
      <Hotspot X="2624.5" Y="-1198.725" Z="373.6781" />
      <Hotspot X="2690.673" Y="-1241.363" Z="375.3259" />
		</Hotspots>
	</Objective>
</Quest>
<Quest Id="30001" Name="Moth-Ridden">
  <Objective Type="KillMob" MobId="57232" KillCount="8">
	  <Hotspots>
      <Hotspot X="857.2562" Y="-2488.644" Z="176.3019" />
      <Hotspot X="818.4035" Y="-2475.059" Z="176.3028" />
      <Hotspot X="851.3853" Y="-2444.993" Z="176.3208" />
      <Hotspot X="850.8632" Y="-2507.412" Z="192.5512" />
      <Hotspot X="811.1708" Y="-2491.723" Z="192.5511" />
      <Hotspot X="849.9635" Y="-2435.728" Z="192.5598" />
		</Hotspots>
	</Objective>
</Quest>
<Quest Id="29997" Name="The Scryer's Dilemma">
	<Objective Type="CollectItem" ItemId="76725" CollectCount="1">
		<CollectFrom>
		  <Mob Id="56820" Name="Water Fiend"  />
		</CollectFrom>
		<Hotspots>
      <Hotspot X="1047.59" Y="-2560.368" Z="174.1573" />
      <Hotspot X="1057.242" Y="-2529.011" Z="170.9273" />
		</Hotspots>
	</Objective>
</Quest>
<Quest Id="29580" Name="Orchard-Supplied Hardware">
	<Objective Type="CollectItem" ItemId="72133" CollectCount="6">
		<CollectFrom>
		  <GameObject Name="Orchard Tool" Id="209344" />
		</CollectFrom>
		<Hotspots>
      <Hotspot X="208.5475" Y="-1573.382" Z="84.22189" />
      <Hotspot X="241.3224" Y="-1631.558" Z="73.7492" />
      <Hotspot X="205.4009" Y="-1658.769" Z="73.23776" />
      <Hotspot X="150.3032" Y="-1655.377" Z="76.09695" />
		</Hotspots>
	</Objective>
</Quest>
<Quest Id="29578" Name="Defiance">
  <Objective Type="KillMob" MobId="54703" KillCount="8">
		<Hotspots>
      <Hotspot X="208.5475" Y="-1573.382" Z="84.22189" />
      <Hotspot X="241.3224" Y="-1631.558" Z="73.7492" />
      <Hotspot X="205.4009" Y="-1658.769" Z="73.23776" />
      <Hotspot X="150.3032" Y="-1655.377" Z="76.09695" />
		</Hotspots>
	</Objective>
  <Objective Type="KillMob" MobId="54702" KillCount="8">
		<Hotspots>
      <Hotspot X="208.5475" Y="-1573.382" Z="84.22189" />
      <Hotspot X="241.3224" Y="-1631.558" Z="73.7492" />
      <Hotspot X="205.4009" Y="-1658.769" Z="73.23776" />
      <Hotspot X="150.3032" Y="-1655.377" Z="76.09695" />
		</Hotspots>
	</Objective>
</Quest>
<Quest Id="29670" Name="Maul Gormal">
  <Objective Type="KillMob" MobId="55016" KillCount="1">
		<Hotspots>
      <Hotspot X="106.6267" Y="-1187.629" Z="4.947461" />
		</Hotspots>
	</Objective>
</Quest>
<!-- ################################### End of Quest Overrides #################################################################### -->
<QuestOrder IgnoreCheckPoints="False" >
  <CustomBehavior File="Cava\LoadProfile" PBL="-1" ProfileName="111-armageddoner85-86thejadeforest-1" /> 
</QuestOrder>
<ProtectedItems>
</ProtectedItems>
</HBProfile>

